{
  "research_name": "Prime Defiant Ability Efficiency",
  "description": "Increases base cost efficiency of the Defiant's active ability.",
  "location": {
    "column": 12,
    "row": 3,
    "tree": "starships"
  },
  "levels": [
    {
      "level": 1,
      "research_time": 6514500,
      "increased_power": 62000,
      "requirements": [
        {
          "name": "R&D Department",
          "level": 35
        }
      ],
      "required_by": [],
      "research_costs": {
        "resources": [
          {
            "type": "dilithium",
            "value": 60000000
          }
        ],
        "materials": [],
        "others": [
          {
            "type": "prime dolamide particle",
            "value": 1200
          }
        ]
      },
      "bonus": {
        "percentage": true,
        "value": 0.5
      }
    }
  ],
  "img_url": "./assets/prime_defiant_ability_efficiency_starships_3_12.png"
}
