{
  "officer_name": "Hugh Culber",
  "description": "",
  "class": "science",
  "group": "discovery crew",
  "faction": "federation",
  "rarity": "uncommon",
  "ability_info": {
    "captain_maneuver": {
      "name": "Protective",
      "bonus": "When defending on a Capture Node, Hugh Culber increases Armor by {value} of the total Health of the Officers on the ship.",
      "percentage": true,
      "value": 0.5
    },
    "officer_ability": {
      "name": "Learned from the Best",
      "bonus": "Hugh increases the Cost Efficiency of Jumping and Summoning with the Discovery by {value}.",
      "percentage": true
    },
    "below_decks_ability": null
  },
  "synergy": {
    "command": 0.5,
    "engineering": 0.5,
    "science": 0.25
  },
  "traits": [
    {
      "name": "Doctor",
      "levels": [
        {
          "level": 1,
          "trait_xp": 1500
        },
        {
          "level": 2,
          "trait_xp": 2700
        },
        {
          "level": 3,
          "trait_xp": 3800
        }
      ],
      "tier": 1
    }
  ],
  "ranks": [
    {
      "rank_id": 1,
      "name": "ENSIGN I",
      "officer_ability_value": 0.05,
      "requirements": {
        "badges": 0,
        "credits": 0,
        "others": [],
        "shards": 10,
        "xp": 0
      }
    },
    {
      "rank_id": 2,
      "name": "LIEUTENANT JG II",
      "officer_ability_value": 0.1,
      "requirements": {
        "badges": 0,
        "credits": 0,
        "others": [],
        "shards": 20,
        "xp": 2500
      }
    },
    {
      "rank_id": 3,
      "name": "LIEUTENANT III",
      "officer_ability_value": 0.15,
      "requirements": {
        "badges": 0,
        "credits": 0,
        "others": [],
        "shards": 40,
        "xp": 50000
      }
    },
    {
      "rank_id": 4,
      "name": "LT. COMMANDER IV",
      "officer_ability_value": 0.2,
      "requirements": {
        "badges": 0,
        "credits": 1000,
        "others": [],
        "shards": 80,
        "xp": 125000
      }
    },
    {
      "rank_id": 5,
      "name": "COMMANDER V",
      "officer_ability_value": 0.25,
      "requirements": {
        "badges": 1,
        "credits": 4000,
        "others": [],
        "shards": 150,
        "xp": 250000
      }
    }
  ],
  "img_url": "./assets/hugh_culber.png"
}
