{
  "building_name": "Astronautics Studio",
  "description": "New ship hulls are researched and unlocked here before becoming available in the Shipyard.",
  "levels": [
    {
      "level": 1,
      "build_time": 24,
      "increased_power": 30,
      "requirements": [
        {
          "name": "Unlock Astronautics",
          "level": 1
        }
      ],
      "build_costs": {
        "resources": [
          {
            "type": "parsteel",
            "value": 5000
          }
        ],
        "materials": [],
        "others": []
      },
      "bonuses": {
        "bonus1": 0.0
      }
    },
    {
      "level": 2,
      "build_time": 95,
      "increased_power": 30,
      "requirements": [
        {
          "name": "Operations",
          "level": 2
        },
        {
          "name": "R&D Department",
          "level": 2
        }
      ],
      "build_costs": {
        "resources": [
          {
            "type": "parsteel",
            "value": 5200
          }
        ],
        "materials": [],
        "others": []
      },
      "bonuses": {
        "bonus1": 0.03
      }
    },
    {
      "level": 3,
      "build_time": 210,
      "increased_power": 35,
      "requirements": [
        {
          "name": "Operations",
          "level": 3
        },
        {
          "name": "R&D Department",
          "level": 3
        }
      ],
      "build_costs": {
        "resources": [
          {
            "type": "parsteel",
            "value": 5400
          }
        ],
        "materials": [],
        "others": []
      },
      "bonuses": {
        "bonus1": 0.04
      }
    },
    {
      "level": 4,
      "build_time": 300,
      "increased_power": 45,
      "requirements": [
        {
          "name": "Operations",
          "level": 4
        },
        {
          "name": "R&D Department",
          "level": 4
        }
      ],
      "build_costs": {
        "resources": [
          {
            "type": "parsteel",
            "value": 5600
          }
        ],
        "materials": [],
        "others": []
      },
      "bonuses": {
        "bonus1": 0.05
      }
    },
    {
      "level": 5,
      "build_time": 540,
      "increased_power": 40,
      "requirements": [
        {
          "name": "Operations",
          "level": 5
        },
        {
          "name": "R&D Department",
          "level": 5
        }
      ],
      "build_costs": {
        "resources": [
          {
            "type": "parsteel",
            "value": 5800
          }
        ],
        "materials": [],
        "others": []
      },
      "bonuses": {
        "bonus1": 0.06
      }
    },
    {
      "level": 6,
      "build_time": 900,
      "increased_power": 60,
      "requirements": [
        {
          "name": "Operations",
          "level": 6
        },
        {
          "name": "R&D Department",
          "level": 6
        }
      ],
      "build_costs": {
        "resources": [
          {
            "type": "parsteel",
            "value": 6000
          }
        ],
        "materials": [],
        "others": []
      },
      "bonuses": {
        "bonus1": 0.08
      }
    },
    {
      "level": 7,
      "build_time": 1680,
      "increased_power": 70,
      "requirements": [
        {
          "name": "Operations",
          "level": 7
        },
        {
          "name": "R&D Department",
          "level": 7
        }
      ],
      "build_costs": {
        "resources": [
          {
            "type": "tritanium",
            "value": 19
          },
          {
            "type": "parsteel",
            "value": 6200
          }
        ],
        "materials": [],
        "others": []
      },
      "bonuses": {
        "bonus1": 0.09
      }
    },
    {
      "level": 8,
      "build_time": 2400,
      "increased_power": 90,
      "requirements": [
        {
          "name": "Operations",
          "level": 8
        },
        {
          "name": "R&D Department",
          "level": 8
        }
      ],
      "build_costs": {
        "resources": [
          {
            "type": "tritanium",
            "value": 60
          },
          {
            "type": "parsteel",
            "value": 6500
          }
        ],
        "materials": [],
        "others": []
      },
      "bonuses": {
        "bonus1": 0.11
      }
    },
    {
      "level": 9,
      "build_time": 3600,
      "increased_power": 100,
      "requirements": [
        {
          "name": "Operations",
          "level": 9
        },
        {
          "name": "R&D Department",
          "level": 9
        }
      ],
      "build_costs": {
        "resources": [
          {
            "type": "tritanium",
            "value": 150
          },
          {
            "type": "parsteel",
            "value": 7000
          }
        ],
        "materials": [],
        "others": []
      },
      "bonuses": {
        "bonus1": 0.12
      }
    },
    {
      "level": 10,
      "build_time": 3960,
      "increased_power": 125,
      "requirements": [
        {
          "name": "Operations",
          "level": 10
        },
        {
          "name": "R&D Department",
          "level": 10
        }
      ],
      "build_costs": {
        "resources": [
          {
            "type": "tritanium",
            "value": 300
          },
          {
            "type": "parsteel",
            "value": 7500
          }
        ],
        "materials": [],
        "others": []
      },
      "bonuses": {
        "bonus1": 0.14
      }
    },
    {
      "level": 11,
      "build_time": 4080,
      "increased_power": 175,
      "requirements": [
        {
          "name": "Operations",
          "level": 11
        },
        {
          "name": "R&D Department",
          "level": 11
        }
      ],
      "build_costs": {
        "resources": [
          {
            "type": "tritanium",
            "value": 400
          },
          {
            "type": "parsteel",
            "value": 9520
          }
        ],
        "materials": [],
        "others": []
      },
      "bonuses": {
        "bonus1": 0.16
      }
    },
    {
      "level": 12,
      "build_time": 7500,
      "increased_power": 175,
      "requirements": [
        {
          "name": "Operations",
          "level": 12
        },
        {
          "name": "R&D Department",
          "level": 12
        }
      ],
      "build_costs": {
        "resources": [
          {
            "type": "tritanium",
            "value": 550
          },
          {
            "type": "parsteel",
            "value": 13090
          }
        ],
        "materials": [],
        "others": []
      },
      "bonuses": {
        "bonus1": 0.18
      }
    },
    {
      "level": 13,
      "build_time": 11100,
      "increased_power": 225,
      "requirements": [
        {
          "name": "Operations",
          "level": 13
        },
        {
          "name": "R&D Department",
          "level": 13
        }
      ],
      "build_costs": {
        "resources": [
          {
            "type": "tritanium",
            "value": 800
          },
          {
            "type": "parsteel",
            "value": 19040
          }
        ],
        "materials": [],
        "others": []
      },
      "bonuses": {
        "bonus1": 0.2
      }
    },
    {
      "level": 14,
      "build_time": 15300,
      "increased_power": 300,
      "requirements": [
        {
          "name": "Operations",
          "level": 14
        },
        {
          "name": "R&D Department",
          "level": 14
        }
      ],
      "build_costs": {
        "resources": [
          {
            "type": "tritanium",
            "value": 1100
          },
          {
            "type": "parsteel",
            "value": 26180
          }
        ],
        "materials": [],
        "others": []
      },
      "bonuses": {
        "bonus1": 0.22
      }
    },
    {
      "level": 15,
      "build_time": 19800,
      "increased_power": 300,
      "requirements": [
        {
          "name": "Operations",
          "level": 15
        },
        {
          "name": "R&D Department",
          "level": 15
        }
      ],
      "build_costs": {
        "resources": [
          {
            "type": "tritanium",
            "value": 1500
          },
          {
            "type": "parsteel",
            "value": 35700
          }
        ],
        "materials": [],
        "others": []
      },
      "bonuses": {
        "bonus1": 0.24
      }
    },
    {
      "level": 16,
      "build_time": 23040,
      "increased_power": 300,
      "requirements": [
        {
          "name": "Operations",
          "level": 16
        },
        {
          "name": "R&D Department",
          "level": 16
        }
      ],
      "build_costs": {
        "resources": [
          {
            "type": "tritanium",
            "value": 2000
          },
          {
            "type": "parsteel",
            "value": 47600
          }
        ],
        "materials": [],
        "others": []
      },
      "bonuses": {
        "bonus1": 0.26
      }
    },
    {
      "level": 17,
      "build_time": 25200,
      "increased_power": 400,
      "requirements": [
        {
          "name": "Operations",
          "level": 17
        },
        {
          "name": "R&D Department",
          "level": 17
        }
      ],
      "build_costs": {
        "resources": [
          {
            "type": "tritanium",
            "value": 2800
          },
          {
            "type": "parsteel",
            "value": 66640
          }
        ],
        "materials": [
          {
            "type": "crystal",
            "value": 25,
            "grade": 2,
            "rarity": "common"
          }
        ],
        "others": []
      },
      "bonuses": {
        "bonus1": 0.29
      }
    },
    {
      "level": 18,
      "build_time": 38160,
      "increased_power": 400,
      "requirements": [
        {
          "name": "Operations",
          "level": 18
        },
        {
          "name": "R&D Department",
          "level": 18
        }
      ],
      "build_costs": {
        "resources": [
          {
            "type": "tritanium",
            "value": 4000
          },
          {
            "type": "parsteel",
            "value": 95200
          }
        ],
        "materials": [
          {
            "type": "crystal",
            "value": 100,
            "grade": 2,
            "rarity": "common"
          }
        ],
        "others": []
      },
      "bonuses": {
        "bonus1": 0.31
      }
    },
    {
      "level": 19,
      "build_time": 55440,
      "increased_power": 600,
      "requirements": [
        {
          "name": "Operations",
          "level": 19
        },
        {
          "name": "R&D Department",
          "level": 19
        }
      ],
      "build_costs": {
        "resources": [
          {
            "type": "tritanium",
            "value": 6000
          },
          {
            "type": "parsteel",
            "value": 142800
          }
        ],
        "materials": [
          {
            "type": "crystal",
            "value": 400,
            "grade": 2,
            "rarity": "common"
          }
        ],
        "others": []
      },
      "bonuses": {
        "bonus1": 0.34
      }
    },
    {
      "level": 20,
      "build_time": 83520,
      "increased_power": 500,
      "requirements": [
        {
          "name": "Operations",
          "level": 20
        },
        {
          "name": "R&D Department",
          "level": 20
        }
      ],
      "build_costs": {
        "resources": [
          {
            "type": "tritanium",
            "value": 8500
          },
          {
            "type": "parsteel",
            "value": 202300
          }
        ],
        "materials": [],
        "others": []
      },
      "bonuses": {
        "bonus1": 0.36
      }
    },
    {
      "level": 21,
      "build_time": 76320,
      "increased_power": 700,
      "requirements": [
        {
          "name": "Operations",
          "level": 21
        },
        {
          "name": "R&D Department",
          "level": 21
        }
      ],
      "build_costs": {
        "resources": [
          {
            "type": "tritanium",
            "value": 14310
          },
          {
            "type": "parsteel",
            "value": 340578
          }
        ],
        "materials": [],
        "others": []
      },
      "bonuses": {
        "bonus1": 0.39
      }
    },
    {
      "level": 22,
      "build_time": 118800,
      "increased_power": 550,
      "requirements": [
        {
          "name": "Operations",
          "level": 22
        },
        {
          "name": "R&D Department",
          "level": 22
        }
      ],
      "build_costs": {
        "resources": [
          {
            "type": "tritanium",
            "value": 22260
          },
          {
            "type": "parsteel",
            "value": 529788
          }
        ],
        "materials": [],
        "others": []
      },
      "bonuses": {
        "bonus1": 0.42
      }
    },
    {
      "level": 23,
      "build_time": 139680,
      "increased_power": 1000,
      "requirements": [
        {
          "name": "Operations",
          "level": 23
        },
        {
          "name": "R&D Department",
          "level": 23
        }
      ],
      "build_costs": {
        "resources": [
          {
            "type": "tritanium",
            "value": 36630
          },
          {
            "type": "parsteel",
            "value": 871794
          }
        ],
        "materials": [],
        "others": []
      },
      "bonuses": {
        "bonus1": 0.45
      }
    },
    {
      "level": 24,
      "build_time": 171360,
      "increased_power": 750,
      "requirements": [
        {
          "name": "Operations",
          "level": 24
        },
        {
          "name": "R&D Department",
          "level": 24
        }
      ],
      "build_costs": {
        "resources": [
          {
            "type": "tritanium",
            "value": 57720
          },
          {
            "type": "parsteel",
            "value": 1373736
          }
        ],
        "materials": [
          {
            "type": "crystal",
            "value": 150,
            "grade": 3,
            "rarity": "common"
          }
        ],
        "others": []
      },
      "bonuses": {
        "bonus1": 0.48
      }
    },
    {
      "level": 25,
      "build_time": 158400,
      "increased_power": 1000,
      "requirements": [
        {
          "name": "Operations",
          "level": 25
        },
        {
          "name": "R&D Department",
          "level": 25
        }
      ],
      "build_costs": {
        "resources": [
          {
            "type": "tritanium",
            "value": 93600
          },
          {
            "type": "parsteel",
            "value": 2227680
          }
        ],
        "materials": [
          {
            "type": "crystal",
            "value": 190,
            "grade": 3,
            "rarity": "common"
          },
          {
            "type": "crystal",
            "value": 1,
            "grade": 3,
            "rarity": "uncommon"
          }
        ],
        "others": []
      },
      "bonuses": {
        "bonus1": 0.51
      }
    },
    {
      "level": 26,
      "build_time": 216000,
      "increased_power": 1000,
      "requirements": [
        {
          "name": "Operations",
          "level": 26
        },
        {
          "name": "R&D Department",
          "level": 26
        }
      ],
      "build_costs": {
        "resources": [
          {
            "type": "tritanium",
            "value": 146250
          },
          {
            "type": "parsteel",
            "value": 3480750
          }
        ],
        "materials": [
          {
            "type": "crystal",
            "value": 4,
            "grade": 3,
            "rarity": "uncommon"
          }
        ],
        "others": []
      },
      "bonuses": {
        "bonus1": 0.55
      }
    },
    {
      "level": 27,
      "build_time": 244800,
      "increased_power": 1250,
      "requirements": [
        {
          "name": "Operations",
          "level": 27
        },
        {
          "name": "R&D Department",
          "level": 27
        }
      ],
      "build_costs": {
        "resources": [
          {
            "type": "tritanium",
            "value": 223200
          },
          {
            "type": "parsteel",
            "value": 5312160
          }
        ],
        "materials": [
          {
            "type": "crystal",
            "value": 290,
            "grade": 3,
            "rarity": "common"
          },
          {
            "type": "crystal",
            "value": 10,
            "grade": 3,
            "rarity": "uncommon"
          }
        ],
        "others": []
      },
      "bonuses": {
        "bonus1": 0.58
      }
    },
    {
      "level": 28,
      "build_time": 285120,
      "increased_power": 1250,
      "requirements": [
        {
          "name": "Operations",
          "level": 28
        },
        {
          "name": "R&D Department",
          "level": 28
        }
      ],
      "build_costs": {
        "resources": [
          {
            "type": "tritanium",
            "value": 334800
          },
          {
            "type": "parsteel",
            "value": 7968240
          }
        ],
        "materials": [
          {
            "type": "crystal",
            "value": 360,
            "grade": 3,
            "rarity": "common"
          },
          {
            "type": "crystal",
            "value": 18,
            "grade": 3,
            "rarity": "uncommon"
          }
        ],
        "others": []
      },
      "bonuses": {
        "bonus1": 0.62
      }
    },
    {
      "level": 29,
      "build_time": 313920,
      "increased_power": 1250,
      "requirements": [
        {
          "name": "Operations",
          "level": 29
        },
        {
          "name": "R&D Department",
          "level": 29
        }
      ],
      "build_costs": {
        "resources": [
          {
            "type": "tritanium",
            "value": 533000
          },
          {
            "type": "parsteel",
            "value": 12685400
          }
        ],
        "materials": [
          {
            "type": "crystal",
            "value": 450,
            "grade": 3,
            "rarity": "common"
          },
          {
            "type": "crystal",
            "value": 30,
            "grade": 3,
            "rarity": "uncommon"
          }
        ],
        "others": []
      },
      "bonuses": {
        "bonus1": 0.65
      }
    },
    {
      "level": 30,
      "build_time": 339840,
      "increased_power": 1500,
      "requirements": [
        {
          "name": "Operations",
          "level": 30
        },
        {
          "name": "R&D Department",
          "level": 30
        },
        {
          "name": "Engine Technology Lab",
          "level": 28
        }
      ],
      "build_costs": {
        "resources": [
          {
            "type": "tritanium",
            "value": 780000
          },
          {
            "type": "parsteel",
            "value": 18564000
          }
        ],
        "materials": [
          {
            "type": "crystal",
            "value": 45,
            "grade": 3,
            "rarity": "uncommon"
          }
        ],
        "others": []
      },
      "bonuses": {
        "bonus1": 0.69
      }
    },
    {
      "level": 31,
      "build_time": 446400,
      "increased_power": 1500,
      "requirements": [
        {
          "name": "Operations",
          "level": 31
        },
        {
          "name": "R&D Department",
          "level": 31
        }
      ],
      "build_costs": {
        "resources": [
          {
            "type": "tritanium",
            "value": 1233000
          },
          {
            "type": "parsteel",
            "value": 29345400
          }
        ],
        "materials": [
          {
            "type": "crystal",
            "value": 700,
            "grade": 3,
            "rarity": "common"
          },
          {
            "type": "crystal",
            "value": 65,
            "grade": 3,
            "rarity": "uncommon"
          }
        ],
        "others": []
      },
      "bonuses": {
        "bonus1": 0.73
      }
    },
    {
      "level": 32,
      "build_time": 436320,
      "increased_power": 1750,
      "requirements": [
        {
          "name": "Operations",
          "level": 32
        },
        {
          "name": "R&D Department",
          "level": 32
        },
        {
          "name": "Foundry",
          "level": 32
        }
      ],
      "build_costs": {
        "resources": [
          {
            "type": "tritanium",
            "value": 1781000
          },
          {
            "type": "parsteel",
            "value": 42387800
          }
        ],
        "materials": [
          {
            "type": "crystal",
            "value": 800,
            "grade": 3,
            "rarity": "common"
          },
          {
            "type": "crystal",
            "value": 87,
            "grade": 3,
            "rarity": "uncommon"
          }
        ],
        "others": []
      },
      "bonuses": {
        "bonus1": 0.77
      }
    },
    {
      "level": 33,
      "build_time": 633600,
      "increased_power": 1750,
      "requirements": [
        {
          "name": "Operations",
          "level": 33
        },
        {
          "name": "R&D Department",
          "level": 33
        }
      ],
      "build_costs": {
        "resources": [
          {
            "type": "tritanium",
            "value": 2755000
          },
          {
            "type": "parsteel",
            "value": 65569000
          }
        ],
        "materials": [
          {
            "type": "crystal",
            "value": 110,
            "grade": 3,
            "rarity": "uncommon"
          }
        ],
        "others": []
      },
      "bonuses": {
        "bonus1": 0.81
      }
    },
    {
      "level": 34,
      "build_time": 839520,
      "increased_power": 2250,
      "requirements": [
        {
          "name": "Operations",
          "level": 34
        },
        {
          "name": "R&D Department",
          "level": 34
        }
      ],
      "build_costs": {
        "resources": [
          {
            "type": "tritanium",
            "value": 4350000
          },
          {
            "type": "parsteel",
            "value": 103530000
          }
        ],
        "materials": [
          {
            "type": "crystal",
            "value": 1100,
            "grade": 3,
            "rarity": "common"
          },
          {
            "type": "crystal",
            "value": 140,
            "grade": 3,
            "rarity": "uncommon"
          }
        ],
        "others": []
      },
      "bonuses": {
        "bonus1": 0.85
      }
    },
    {
      "level": 35,
      "build_time": 1107360,
      "increased_power": 2000,
      "requirements": [
        {
          "name": "Operations",
          "level": 35
        },
        {
          "name": "R&D Department",
          "level": 35
        }
      ],
      "build_costs": {
        "resources": [
          {
            "type": "tritanium",
            "value": 6732000
          },
          {
            "type": "parsteel",
            "value": 160221600
          }
        ],
        "materials": [
          {
            "type": "crystal",
            "value": 180,
            "grade": 3,
            "rarity": "uncommon"
          }
        ],
        "others": []
      },
      "bonuses": {
        "bonus1": 0.89
      }
    },
    {
      "level": 36,
      "build_time": 1414080,
      "increased_power": 2000,
      "requirements": [
        {
          "name": "Operations",
          "level": 36
        },
        {
          "name": "R&D Department",
          "level": 36
        },
        {
          "name": "Engine Technology Lab",
          "level": 36
        }
      ],
      "build_costs": {
        "resources": [
          {
            "type": "tritanium",
            "value": 9486000
          },
          {
            "type": "parsteel",
            "value": 225766800
          }
        ],
        "materials": [
          {
            "type": "crystal",
            "value": 220,
            "grade": 3,
            "rarity": "uncommon"
          }
        ],
        "others": []
      },
      "bonuses": {
        "bonus1": 0.93
      }
    },
    {
      "level": 37,
      "build_time": 1461600,
      "increased_power": 2500,
      "requirements": [
        {
          "name": "Operations",
          "level": 37
        },
        {
          "name": "R&D Department",
          "level": 37
        }
      ],
      "build_costs": {
        "resources": [
          {
            "type": "tritanium",
            "value": 14580000
          },
          {
            "type": "parsteel",
            "value": 347004000
          }
        ],
        "materials": [
          {
            "type": "crystal",
            "value": 1800,
            "grade": 3,
            "rarity": "common"
          },
          {
            "type": "crystal",
            "value": 260,
            "grade": 3,
            "rarity": "uncommon"
          }
        ],
        "others": []
      },
      "bonuses": {
        "bonus1": 0.98
      }
    },
    {
      "level": 38,
      "build_time": 2370240,
      "increased_power": 2500,
      "requirements": [
        {
          "name": "Operations",
          "level": 38
        },
        {
          "name": "R&D Department",
          "level": 38
        }
      ],
      "build_costs": {
        "resources": [
          {
            "type": "tritanium",
            "value": 22680000
          },
          {
            "type": "parsteel",
            "value": 539784000
          }
        ],
        "materials": [
          {
            "type": "crystal",
            "value": 2100,
            "grade": 3,
            "rarity": "common"
          },
          {
            "type": "crystal",
            "value": 310,
            "grade": 3,
            "rarity": "uncommon"
          }
        ],
        "others": []
      },
      "bonuses": {
        "bonus1": 1.02
      }
    },
    {
      "level": 39,
      "build_time": 3146400,
      "increased_power": 2500,
      "requirements": [
        {
          "name": "Operations",
          "level": 39
        },
        {
          "name": "R&D Department",
          "level": 39
        }
      ],
      "build_costs": {
        "resources": [
          {
            "type": "tritanium",
            "value": 38700000
          },
          {
            "type": "parsteel",
            "value": 921060000
          }
        ],
        "materials": [
          {
            "type": "crystal",
            "value": 2500,
            "grade": 3,
            "rarity": "common"
          },
          {
            "type": "crystal",
            "value": 360,
            "grade": 3,
            "rarity": "uncommon"
          }
        ],
        "others": []
      },
      "bonuses": {
        "bonus1": 1.07
      }
    },
    {
      "level": 40,
      "build_time": 5584320,
      "increased_power": 3000,
      "requirements": [
        {
          "name": "Operations",
          "level": 40
        },
        {
          "name": "R&D Department",
          "level": 40
        }
      ],
      "build_costs": {
        "resources": [
          {
            "type": "tritanium",
            "value": 60200000
          },
          {
            "type": "parsteel",
            "value": 4011728000
          }
        ],
        "materials": [
          {
            "type": "crystal",
            "value": 6000,
            "grade": 4,
            "rarity": "uncommon"
          },
          {
            "type": "crystal",
            "value": 10000,
            "grade": 4,
            "rarity": "common"
          }
        ],
        "others": []
      },
      "bonuses": {
        "bonus1": 1.11
      }
    },
    {
      "level": 41,
      "build_time": 5234400,
      "increased_power": 3000,
      "requirements": [
        {
          "name": "Operations",
          "level": 41
        },
        {
          "name": "R&D Department",
          "level": 41
        }
      ],
      "build_costs": {
        "resources": [
          {
            "type": "tritanium",
            "value": 86000000
          },
          {
            "type": "parsteel",
            "value": 4093600000
          }
        ],
        "materials": [
          {
            "type": "crystal",
            "value": 7000,
            "grade": 4,
            "rarity": "uncommon"
          },
          {
            "type": "crystal",
            "value": 20000,
            "grade": 4,
            "rarity": "common"
          }
        ],
        "others": []
      },
      "bonuses": {
        "bonus1": 1.16
      }
    },
    {
      "level": 42,
      "build_time": 8045280,
      "increased_power": 3500,
      "requirements": [
        {
          "name": "Operations",
          "level": 42
        },
        {
          "name": "R&D Department",
          "level": 42
        },
        {
          "name": "Foundry",
          "level": 42
        }
      ],
      "build_costs": {
        "resources": [
          {
            "type": "tritanium",
            "value": 128100000
          },
          {
            "type": "parsteel",
            "value": 6097560000
          }
        ],
        "materials": [
          {
            "type": "crystal",
            "value": 8000,
            "grade": 4,
            "rarity": "uncommon"
          },
          {
            "type": "crystal",
            "value": 30000,
            "grade": 4,
            "rarity": "common"
          }
        ],
        "others": []
      },
      "bonuses": {
        "bonus1": 1.21
      }
    },
    {
      "level": 43,
      "build_time": 10630080,
      "increased_power": 3500,
      "requirements": [
        {
          "name": "Operations",
          "level": 43
        },
        {
          "name": "R&D Department",
          "level": 43
        }
      ],
      "build_costs": {
        "resources": [
          {
            "type": "tritanium",
            "value": 183000000
          },
          {
            "type": "parsteel",
            "value": 8710800000
          }
        ],
        "materials": [
          {
            "type": "crystal",
            "value": 9000,
            "grade": 4,
            "rarity": "uncommon"
          },
          {
            "type": "crystal",
            "value": 40000,
            "grade": 4,
            "rarity": "common"
          }
        ],
        "others": []
      },
      "bonuses": {
        "bonus1": 1.26
      }
    },
    {
      "level": 44,
      "build_time": 13874400,
      "increased_power": 3500,
      "requirements": [
        {
          "name": "Operations",
          "level": 44
        },
        {
          "name": "R&D Department",
          "level": 44
        }
      ],
      "build_costs": {
        "resources": [
          {
            "type": "tritanium",
            "value": 274500000
          },
          {
            "type": "parsteel",
            "value": 13066200000
          }
        ],
        "materials": [
          {
            "type": "crystal",
            "value": 10000,
            "grade": 4,
            "rarity": "uncommon"
          },
          {
            "type": "crystal",
            "value": 50000,
            "grade": 4,
            "rarity": "common"
          }
        ],
        "others": []
      },
      "bonuses": {
        "bonus1": 1.31
      }
    },
    {
      "level": 45,
      "build_time": 17912160,
      "increased_power": 3500,
      "requirements": [
        {
          "name": "Operations",
          "level": 45
        },
        {
          "name": "R&D Department",
          "level": 45
        }
      ],
      "build_costs": {
        "resources": [
          {
            "type": "tritanium",
            "value": 390000000
          },
          {
            "type": "parsteel",
            "value": 18564000000
          }
        ],
        "materials": [
          {
            "type": "crystal",
            "value": 25000,
            "grade": 4,
            "rarity": "common"
          }
        ],
        "others": []
      },
      "bonuses": {
        "bonus1": 1.37
      }
    },
    {
      "level": 46,
      "build_time": 22896000,
      "increased_power": 4000,
      "requirements": [
        {
          "name": "Operations",
          "level": 46
        },
        {
          "name": "R&D Department",
          "level": 46
        }
      ],
      "build_costs": {
        "resources": [
          {
            "type": "tritanium",
            "value": 536250000
          },
          {
            "type": "parsteel",
            "value": 25525500000
          }
        ],
        "materials": [
          {
            "type": "crystal",
            "value": 30000,
            "grade": 4,
            "rarity": "common"
          }
        ],
        "others": []
      },
      "bonuses": {
        "bonus1": 1.43
      }
    },
    {
      "level": 47,
      "build_time": 29004480,
      "increased_power": 4000,
      "requirements": [
        {
          "name": "Operations",
          "level": 47
        },
        {
          "name": "R&D Department",
          "level": 47
        },
        {
          "name": "Engine Technology Lab",
          "level": 47
        }
      ],
      "build_costs": {
        "resources": [
          {
            "type": "tritanium",
            "value": 780000000
          },
          {
            "type": "parsteel",
            "value": 37128000000
          }
        ],
        "materials": [
          {
            "type": "crystal",
            "value": 35000,
            "grade": 4,
            "rarity": "common"
          }
        ],
        "others": []
      },
      "bonuses": {
        "bonus1": 1.49
      }
    },
    {
      "level": 48,
      "build_time": 36440640,
      "increased_power": 5000,
      "requirements": [
        {
          "name": "Operations",
          "level": 48
        },
        {
          "name": "R&D Department",
          "level": 48
        },
        {
          "name": "Science Lab",
          "level": 48
        }
      ],
      "build_costs": {
        "resources": [
          {
            "type": "tritanium",
            "value": 1260000000
          },
          {
            "type": "parsteel",
            "value": 59976000000
          }
        ],
        "materials": [
          {
            "type": "crystal",
            "value": 40000,
            "grade": 4,
            "rarity": "common"
          }
        ],
        "others": []
      },
      "bonuses": {
        "bonus1": 1.55
      }
    },
    {
      "level": 49,
      "build_time": 45434880,
      "increased_power": 4000,
      "requirements": [
        {
          "name": "Operations",
          "level": 49
        },
        {
          "name": "R&D Department",
          "level": 49
        },
        {
          "name": "Foundry",
          "level": 49
        }
      ],
      "build_costs": {
        "resources": [
          {
            "type": "tritanium",
            "value": 2100000000
          },
          {
            "type": "parsteel",
            "value": 99960000000
          }
        ],
        "materials": [
          {
            "type": "crystal",
            "value": 45000,
            "grade": 4,
            "rarity": "common"
          }
        ],
        "others": []
      },
      "bonuses": {
        "bonus1": 1.61
      }
    },
    {
      "level": 50,
      "build_time": 56250720,
      "increased_power": 5000,
      "requirements": [
        {
          "name": "Operations",
          "level": 50
        },
        {
          "name": "R&D Department",
          "level": 50
        }
      ],
      "build_costs": {
        "resources": [
          {
            "type": "tritanium",
            "value": 3675000000
          },
          {
            "type": "parsteel",
            "value": 174930000000
          }
        ],
        "materials": [],
        "others": []
      },
      "bonuses": {
        "bonus1": 1.7
      }
    },
    {
      "level": 51,
      "build_time": 59626080,
      "increased_power": 5000,
      "requirements": [
        {
          "name": "Operations",
          "level": 51
        },
        {
          "name": "R&D Department",
          "level": 51
        }
      ],
      "build_costs": {
        "resources": [
          {
            "type": "tritanium",
            "value": 7800000000
          },
          {
            "type": "parsteel",
            "value": 872508000000
          }
        ],
        "materials": [
          {
            "type": "crystal",
            "value": 11000,
            "grade": 5,
            "rarity": "common"
          }
        ],
        "others": []
      },
      "bonuses": {
        "bonus1": 1.77
      }
    },
    {
      "level": 52,
      "build_time": 63204480,
      "increased_power": 6000,
      "requirements": [
        {
          "name": "Operations",
          "level": 52
        },
        {
          "name": "R&D Department",
          "level": 52
        }
      ],
      "build_costs": {
        "resources": [
          {
            "type": "tritanium",
            "value": 13260000000
          },
          {
            "type": "parsteel",
            "value": 1577940000000
          }
        ],
        "materials": [
          {
            "type": "crystal",
            "value": 19000,
            "grade": 5,
            "rarity": "common"
          }
        ],
        "others": []
      },
      "bonuses": {
        "bonus1": 1.84
      }
    },
    {
      "level": 53,
      "build_time": 66996000,
      "increased_power": 5000,
      "requirements": [
        {
          "name": "Science Lab",
          "level": 52
        },
        {
          "name": "Engine Technology Lab",
          "level": 52
        },
        {
          "name": "Foundry",
          "level": 52
        }
      ],
      "build_costs": {
        "resources": [
          {
            "type": "tritanium",
            "value": 23200000000
          },
          {
            "type": "parsteel",
            "value": 2650368000000
          }
        ],
        "materials": [
          {
            "type": "crystal",
            "value": 36600,
            "grade": 5,
            "rarity": "common"
          }
        ],
        "others": []
      },
      "bonuses": {
        "bonus1": 1.91
      }
    },
    {
      "level": 54,
      "build_time": 71016480,
      "increased_power": 6000,
      "requirements": [
        {
          "name": "Operations",
          "level": 54
        },
        {
          "name": "R&D Department",
          "level": 54
        }
      ],
      "build_costs": {
        "resources": [
          {
            "type": "tritanium",
            "value": 34800000000
          },
          {
            "type": "parsteel",
            "value": 3975552000000
          }
        ],
        "materials": [
          {
            "type": "crystal",
            "value": 11200,
            "grade": 5,
            "rarity": "rare"
          },
          {
            "type": "crystal",
            "value": 48400,
            "grade": 5,
            "rarity": "common"
          }
        ],
        "others": []
      },
      "bonuses": {
        "bonus1": 1.98
      }
    },
    {
      "level": 55,
      "build_time": 75277440,
      "increased_power": 6000,
      "requirements": [
        {
          "name": "Operations",
          "level": 55
        },
        {
          "name": "R&D Department",
          "level": 55
        }
      ],
      "build_costs": {
        "resources": [
          {
            "type": "tritanium",
            "value": 54600000000
          },
          {
            "type": "parsteel",
            "value": 6757296000000
          }
        ],
        "materials": [
          {
            "type": "crystal",
            "value": 40000,
            "grade": 5,
            "rarity": "uncommon"
          },
          {
            "type": "crystal",
            "value": 13600,
            "grade": 5,
            "rarity": "rare"
          }
        ],
        "others": []
      },
      "bonuses": {
        "bonus1": 2.05
      }
    },
    {
      "level": 56,
      "build_time": 79793280,
      "increased_power": 6000,
      "requirements": [
        {
          "name": "Operations",
          "level": 56
        },
        {
          "name": "R&D Department",
          "level": 56
        }
      ],
      "build_costs": {
        "resources": [
          {
            "type": "tritanium",
            "value": 85800000000
          },
          {
            "type": "parsteel",
            "value": 10618608000000
          }
        ],
        "materials": [
          {
            "type": "crystal",
            "value": 44200,
            "grade": 5,
            "rarity": "uncommon"
          },
          {
            "type": "crystal",
            "value": 13000,
            "grade": 5,
            "rarity": "rare"
          }
        ],
        "others": []
      },
      "bonuses": {
        "bonus1": 2.13
      }
    },
    {
      "level": 57,
      "build_time": 84581280,
      "increased_power": 7000,
      "requirements": [
        {
          "name": "Operations",
          "level": 57
        },
        {
          "name": "R&D Department",
          "level": 57
        },
        {
          "name": "Engine Technology Lab",
          "level": 57
        }
      ],
      "build_costs": {
        "resources": [
          {
            "type": "tritanium",
            "value": 134320000000
          },
          {
            "type": "parsteel",
            "value": 16623443200000
          }
        ],
        "materials": [
          {
            "type": "crystal",
            "value": 55400,
            "grade": 5,
            "rarity": "uncommon"
          },
          {
            "type": "crystal",
            "value": 18200,
            "grade": 5,
            "rarity": "rare"
          }
        ],
        "others": []
      },
      "bonuses": {
        "bonus1": 2.21
      }
    },
    {
      "level": 58,
      "build_time": 89655840,
      "increased_power": 7000,
      "requirements": [
        {
          "name": "Operations",
          "level": 58
        },
        {
          "name": "R&D Department",
          "level": 58
        },
        {
          "name": "Science Lab",
          "level": 58
        }
      ],
      "build_costs": {
        "resources": [
          {
            "type": "tritanium",
            "value": 210240000000
          },
          {
            "type": "parsteel",
            "value": 24017817600000
          }
        ],
        "materials": [
          {
            "type": "crystal",
            "value": 66100,
            "grade": 5,
            "rarity": "uncommon"
          },
          {
            "type": "crystal",
            "value": 14800,
            "grade": 5,
            "rarity": "rare"
          }
        ],
        "others": []
      },
      "bonuses": {
        "bonus1": 2.29
      }
    },
    {
      "level": 59,
      "build_time": 95035680,
      "increased_power": 7000,
      "requirements": [
        {
          "name": "Operations",
          "level": 59
        },
        {
          "name": "R&D Department",
          "level": 59
        },
        {
          "name": "Foundry",
          "level": 59
        }
      ],
      "build_costs": {
        "resources": [
          {
            "type": "tritanium",
            "value": 315360000000
          },
          {
            "type": "parsteel",
            "value": 36026726400000
          }
        ],
        "materials": [
          {
            "type": "crystal",
            "value": 21300,
            "grade": 5,
            "rarity": "rare"
          },
          {
            "type": "crystal",
            "value": 141900,
            "grade": 5,
            "rarity": "common"
          }
        ],
        "others": []
      },
      "bonuses": {
        "bonus1": 2.37
      }
    },
    {
      "level": 60,
      "build_time": 100738080,
      "increased_power": 8000,
      "requirements": [
        {
          "name": "Operations",
          "level": 60
        },
        {
          "name": "R&D Department",
          "level": 60
        }
      ],
      "build_costs": {
        "resources": [
          {
            "type": "tritanium",
            "value": 492500000000
          },
          {
            "type": "parsteel",
            "value": 56263200000000
          }
        ],
        "materials": [
          {
            "type": "crystal",
            "value": 24400,
            "grade": 5,
            "rarity": "rare"
          },
          {
            "type": "crystal",
            "value": 138200,
            "grade": 5,
            "rarity": "common"
          }
        ],
        "others": []
      },
      "bonuses": {
        "bonus1": 2.45
      }
    }
  ],
  "bonuses": {
    "bonus1": {
      "name": "Research Cost Efficiency",
      "percentage": true
    }
  }
}
