{
  "building_name": "Dilithium Generator E",
  "description": "Produces Dilithium, a crystalline mineral required when researching new technologies and building advanced ship components. Upgrading Dilithium Generators increases the amount that is produced, and unlocks the production of \u03a3-Dilithium at high levels.",
  "levels": [
    {
      "level": 1,
      "build_time": 45,
      "increased_power": 10,
      "requirements": [
        {
          "name": "Operations",
          "level": 40
        },
        {
          "name": "Dilithium Generator C",
          "level": 1
        }
      ],
      "build_costs": {
        "resources": [
          {
            "type": "tritanium",
            "value": 300
          },
          {
            "type": "parsteel",
            "value": 400
          }
        ],
        "materials": [],
        "others": []
      },
      "bonuses": {
        "bonus1": 0,
        "bonus2": 0,
        "bonus3": 2,
        "bonus4": 1
      }
    },
    {
      "level": 2,
      "build_time": 120,
      "increased_power": 10,
      "requirements": [
        {
          "name": "Operations",
          "level": 2
        },
        {
          "name": "Dilithium Generator C",
          "level": 2
        }
      ],
      "build_costs": {
        "resources": [
          {
            "type": "tritanium",
            "value": 350
          },
          {
            "type": "parsteel",
            "value": 500
          }
        ],
        "materials": [],
        "others": []
      },
      "bonuses": {
        "bonus1": 0,
        "bonus2": 0,
        "bonus3": 4,
        "bonus4": 2
      }
    },
    {
      "level": 3,
      "build_time": 210,
      "increased_power": 12,
      "requirements": [
        {
          "name": "Operations",
          "level": 3
        },
        {
          "name": "Dilithium Generator C",
          "level": 3
        }
      ],
      "build_costs": {
        "resources": [
          {
            "type": "tritanium",
            "value": 400
          },
          {
            "type": "parsteel",
            "value": 600
          }
        ],
        "materials": [],
        "others": []
      },
      "bonuses": {
        "bonus1": 0,
        "bonus2": 0,
        "bonus3": 6,
        "bonus4": 6
      }
    },
    {
      "level": 4,
      "build_time": 300,
      "increased_power": 13,
      "requirements": [
        {
          "name": "Operations",
          "level": 4
        },
        {
          "name": "Dilithium Generator C",
          "level": 4
        }
      ],
      "build_costs": {
        "resources": [
          {
            "type": "tritanium",
            "value": 450
          },
          {
            "type": "parsteel",
            "value": 700
          }
        ],
        "materials": [],
        "others": []
      },
      "bonuses": {
        "bonus1": 0,
        "bonus2": 0,
        "bonus3": 8,
        "bonus4": 13
      }
    },
    {
      "level": 5,
      "build_time": 540,
      "increased_power": 15,
      "requirements": [
        {
          "name": "Operations",
          "level": 5
        },
        {
          "name": "Dilithium Generator C",
          "level": 5
        }
      ],
      "build_costs": {
        "resources": [
          {
            "type": "tritanium",
            "value": 500
          },
          {
            "type": "parsteel",
            "value": 800
          }
        ],
        "materials": [],
        "others": []
      },
      "bonuses": {
        "bonus1": 0,
        "bonus2": 0,
        "bonus3": 12,
        "bonus4": 24
      }
    },
    {
      "level": 6,
      "build_time": 900,
      "increased_power": 20,
      "requirements": [
        {
          "name": "Operations",
          "level": 6
        },
        {
          "name": "Dilithium Generator C",
          "level": 6
        }
      ],
      "build_costs": {
        "resources": [
          {
            "type": "tritanium",
            "value": 550
          },
          {
            "type": "parsteel",
            "value": 1000
          }
        ],
        "materials": [],
        "others": []
      },
      "bonuses": {
        "bonus1": 0,
        "bonus2": 0,
        "bonus3": 15,
        "bonus4": 36
      }
    },
    {
      "level": 7,
      "build_time": 1680,
      "increased_power": 20,
      "requirements": [
        {
          "name": "Operations",
          "level": 7
        },
        {
          "name": "Dilithium Generator C",
          "level": 7
        }
      ],
      "build_costs": {
        "resources": [
          {
            "type": "tritanium",
            "value": 600
          },
          {
            "type": "parsteel",
            "value": 1200
          }
        ],
        "materials": [],
        "others": []
      },
      "bonuses": {
        "bonus1": 0,
        "bonus2": 0,
        "bonus3": 17,
        "bonus4": 48
      }
    },
    {
      "level": 8,
      "build_time": 2400,
      "increased_power": 30,
      "requirements": [
        {
          "name": "Operations",
          "level": 8
        },
        {
          "name": "Dilithium Generator C",
          "level": 8
        }
      ],
      "build_costs": {
        "resources": [
          {
            "type": "tritanium",
            "value": 650
          },
          {
            "type": "parsteel",
            "value": 1400
          }
        ],
        "materials": [],
        "others": []
      },
      "bonuses": {
        "bonus1": 0,
        "bonus2": 0,
        "bonus3": 20,
        "bonus4": 64
      }
    },
    {
      "level": 9,
      "build_time": 3600,
      "increased_power": 40,
      "requirements": [
        {
          "name": "Operations",
          "level": 9
        },
        {
          "name": "Dilithium Generator C",
          "level": 9
        }
      ],
      "build_costs": {
        "resources": [
          {
            "type": "tritanium",
            "value": 700
          },
          {
            "type": "parsteel",
            "value": 1600
          }
        ],
        "materials": [],
        "others": []
      },
      "bonuses": {
        "bonus1": 0,
        "bonus2": 0,
        "bonus3": 22,
        "bonus4": 79
      }
    },
    {
      "level": 10,
      "build_time": 3960,
      "increased_power": 40,
      "requirements": [
        {
          "name": "Operations",
          "level": 10
        },
        {
          "name": "Dilithium Generator C",
          "level": 10
        }
      ],
      "build_costs": {
        "resources": [
          {
            "type": "tritanium",
            "value": 1500
          },
          {
            "type": "parsteel",
            "value": 2000
          }
        ],
        "materials": [],
        "others": []
      },
      "bonuses": {
        "bonus1": 0,
        "bonus2": 0,
        "bonus3": 37,
        "bonus4": 150
      }
    },
    {
      "level": 11,
      "build_time": 4080,
      "increased_power": 50,
      "requirements": [
        {
          "name": "Operations",
          "level": 11
        },
        {
          "name": "Dilithium Generator C",
          "level": 11
        }
      ],
      "build_costs": {
        "resources": [
          {
            "type": "tritanium",
            "value": 2000
          },
          {
            "type": "parsteel",
            "value": 2720
          }
        ],
        "materials": [],
        "others": []
      },
      "bonuses": {
        "bonus1": 0,
        "bonus2": 0,
        "bonus3": 40,
        "bonus4": 170
      }
    },
    {
      "level": 12,
      "build_time": 7500,
      "increased_power": 70,
      "requirements": [
        {
          "name": "Operations",
          "level": 12
        },
        {
          "name": "Dilithium Generator C",
          "level": 12
        }
      ],
      "build_costs": {
        "resources": [
          {
            "type": "tritanium",
            "value": 2750
          },
          {
            "type": "parsteel",
            "value": 3740
          }
        ],
        "materials": [],
        "others": []
      },
      "bonuses": {
        "bonus1": 0,
        "bonus2": 0,
        "bonus3": 44,
        "bonus4": 195
      }
    },
    {
      "level": 13,
      "build_time": 11100,
      "increased_power": 70,
      "requirements": [
        {
          "name": "Operations",
          "level": 13
        },
        {
          "name": "Dilithium Generator C",
          "level": 13
        }
      ],
      "build_costs": {
        "resources": [
          {
            "type": "tritanium",
            "value": 4000
          },
          {
            "type": "parsteel",
            "value": 5440
          }
        ],
        "materials": [],
        "others": []
      },
      "bonuses": {
        "bonus1": 0,
        "bonus2": 0,
        "bonus3": 48,
        "bonus4": 230
      }
    },
    {
      "level": 14,
      "build_time": 15300,
      "increased_power": 90,
      "requirements": [
        {
          "name": "Operations",
          "level": 14
        },
        {
          "name": "Dilithium Generator C",
          "level": 14
        }
      ],
      "build_costs": {
        "resources": [
          {
            "type": "tritanium",
            "value": 5500
          },
          {
            "type": "parsteel",
            "value": 7480
          }
        ],
        "materials": [],
        "others": []
      },
      "bonuses": {
        "bonus1": 0,
        "bonus2": 0,
        "bonus3": 52,
        "bonus4": 280
      }
    },
    {
      "level": 15,
      "build_time": 19800,
      "increased_power": 85,
      "requirements": [
        {
          "name": "Operations",
          "level": 15
        },
        {
          "name": "Dilithium Generator C",
          "level": 15
        }
      ],
      "build_costs": {
        "resources": [
          {
            "type": "tritanium",
            "value": 7500
          },
          {
            "type": "parsteel",
            "value": 10200
          }
        ],
        "materials": [],
        "others": []
      },
      "bonuses": {
        "bonus1": 0,
        "bonus2": 0,
        "bonus3": 61,
        "bonus4": 355
      }
    },
    {
      "level": 16,
      "build_time": 23040,
      "increased_power": 125,
      "requirements": [
        {
          "name": "Operations",
          "level": 16
        },
        {
          "name": "Dilithium Generator C",
          "level": 16
        }
      ],
      "build_costs": {
        "resources": [
          {
            "type": "tritanium",
            "value": 10000
          },
          {
            "type": "parsteel",
            "value": 13600
          }
        ],
        "materials": [],
        "others": []
      },
      "bonuses": {
        "bonus1": 0,
        "bonus2": 0,
        "bonus3": 66,
        "bonus4": 410
      }
    },
    {
      "level": 17,
      "build_time": 25200,
      "increased_power": 125,
      "requirements": [
        {
          "name": "Operations",
          "level": 17
        },
        {
          "name": "Dilithium Generator C",
          "level": 17
        }
      ],
      "build_costs": {
        "resources": [
          {
            "type": "tritanium",
            "value": 14000
          },
          {
            "type": "parsteel",
            "value": 19040
          }
        ],
        "materials": [],
        "others": []
      },
      "bonuses": {
        "bonus1": 0,
        "bonus2": 0,
        "bonus3": 70,
        "bonus4": 460
      }
    },
    {
      "level": 18,
      "build_time": 38160,
      "increased_power": 150,
      "requirements": [
        {
          "name": "Operations",
          "level": 18
        },
        {
          "name": "Dilithium Generator C",
          "level": 18
        }
      ],
      "build_costs": {
        "resources": [
          {
            "type": "tritanium",
            "value": 20000
          },
          {
            "type": "parsteel",
            "value": 27200
          }
        ],
        "materials": [],
        "others": []
      },
      "bonuses": {
        "bonus1": 0,
        "bonus2": 0,
        "bonus3": 74,
        "bonus4": 530
      }
    },
    {
      "level": 19,
      "build_time": 55440,
      "increased_power": 175,
      "requirements": [
        {
          "name": "Operations",
          "level": 19
        },
        {
          "name": "Dilithium Generator C",
          "level": 19
        }
      ],
      "build_costs": {
        "resources": [
          {
            "type": "tritanium",
            "value": 30000
          },
          {
            "type": "parsteel",
            "value": 40800
          }
        ],
        "materials": [],
        "others": []
      },
      "bonuses": {
        "bonus1": 0,
        "bonus2": 0,
        "bonus3": 78,
        "bonus4": 590
      }
    },
    {
      "level": 20,
      "build_time": 83520,
      "increased_power": 200,
      "requirements": [
        {
          "name": "Operations",
          "level": 20
        },
        {
          "name": "Dilithium Generator C",
          "level": 20
        }
      ],
      "build_costs": {
        "resources": [
          {
            "type": "tritanium",
            "value": 42500
          },
          {
            "type": "parsteel",
            "value": 57800
          }
        ],
        "materials": [],
        "others": []
      },
      "bonuses": {
        "bonus1": 0,
        "bonus2": 0,
        "bonus3": 98,
        "bonus4": 780
      }
    },
    {
      "level": 21,
      "build_time": 76320,
      "increased_power": 250,
      "requirements": [
        {
          "name": "Operations",
          "level": 21
        },
        {
          "name": "Dilithium Generator C",
          "level": 21
        }
      ],
      "build_costs": {
        "resources": [
          {
            "type": "tritanium",
            "value": 71550
          },
          {
            "type": "parsteel",
            "value": 97308
          }
        ],
        "materials": [],
        "others": []
      },
      "bonuses": {
        "bonus1": 0,
        "bonus2": 0,
        "bonus3": 105,
        "bonus4": 860
      }
    },
    {
      "level": 22,
      "build_time": 118800,
      "increased_power": 200,
      "requirements": [
        {
          "name": "Operations",
          "level": 22
        },
        {
          "name": "Dilithium Generator C",
          "level": 22
        }
      ],
      "build_costs": {
        "resources": [
          {
            "type": "tritanium",
            "value": 111300
          },
          {
            "type": "parsteel",
            "value": 151368
          }
        ],
        "materials": [],
        "others": []
      },
      "bonuses": {
        "bonus1": 0,
        "bonus2": 0,
        "bonus3": 110,
        "bonus4": 900
      }
    },
    {
      "level": 23,
      "build_time": 139680,
      "increased_power": 300,
      "requirements": [
        {
          "name": "Operations",
          "level": 23
        },
        {
          "name": "Dilithium Generator C",
          "level": 23
        }
      ],
      "build_costs": {
        "resources": [
          {
            "type": "tritanium",
            "value": 183150
          },
          {
            "type": "parsteel",
            "value": 249084
          }
        ],
        "materials": [],
        "others": []
      },
      "bonuses": {
        "bonus1": 0,
        "bonus2": 0,
        "bonus3": 115,
        "bonus4": 970
      }
    },
    {
      "level": 24,
      "build_time": 171360,
      "increased_power": 200,
      "requirements": [
        {
          "name": "Operations",
          "level": 24
        },
        {
          "name": "Dilithium Generator C",
          "level": 24
        }
      ],
      "build_costs": {
        "resources": [
          {
            "type": "tritanium",
            "value": 288600
          },
          {
            "type": "parsteel",
            "value": 392496
          }
        ],
        "materials": [],
        "others": []
      },
      "bonuses": {
        "bonus1": 0,
        "bonus2": 0,
        "bonus3": 120,
        "bonus4": 1010
      }
    },
    {
      "level": 25,
      "build_time": 158400,
      "increased_power": 400,
      "requirements": [
        {
          "name": "Operations",
          "level": 25
        },
        {
          "name": "Dilithium Generator C",
          "level": 25
        }
      ],
      "build_costs": {
        "resources": [
          {
            "type": "tritanium",
            "value": 468000
          },
          {
            "type": "parsteel",
            "value": 636480
          }
        ],
        "materials": [],
        "others": []
      },
      "bonuses": {
        "bonus1": 0,
        "bonus2": 0,
        "bonus3": 145,
        "bonus4": 1250
      }
    },
    {
      "level": 26,
      "build_time": 216000,
      "increased_power": 300,
      "requirements": [
        {
          "name": "Operations",
          "level": 26
        },
        {
          "name": "Dilithium Generator C",
          "level": 26
        }
      ],
      "build_costs": {
        "resources": [
          {
            "type": "tritanium",
            "value": 731250
          },
          {
            "type": "parsteel",
            "value": 994500
          }
        ],
        "materials": [],
        "others": []
      },
      "bonuses": {
        "bonus1": 0,
        "bonus2": 0,
        "bonus3": 150,
        "bonus4": 1290
      }
    },
    {
      "level": 27,
      "build_time": 244800,
      "increased_power": 400,
      "requirements": [
        {
          "name": "Operations",
          "level": 27
        },
        {
          "name": "Dilithium Generator C",
          "level": 27
        }
      ],
      "build_costs": {
        "resources": [
          {
            "type": "tritanium",
            "value": 1116000
          },
          {
            "type": "parsteel",
            "value": 1517760
          }
        ],
        "materials": [],
        "others": []
      },
      "bonuses": {
        "bonus1": 0,
        "bonus2": 0,
        "bonus3": 155,
        "bonus4": 1360
      }
    },
    {
      "level": 28,
      "build_time": 285120,
      "increased_power": 400,
      "requirements": [
        {
          "name": "Operations",
          "level": 28
        },
        {
          "name": "Dilithium Generator C",
          "level": 28
        }
      ],
      "build_costs": {
        "resources": [
          {
            "type": "tritanium",
            "value": 1674000
          },
          {
            "type": "parsteel",
            "value": 2276640
          }
        ],
        "materials": [],
        "others": []
      },
      "bonuses": {
        "bonus1": 0,
        "bonus2": 0,
        "bonus3": 160,
        "bonus4": 1400
      }
    },
    {
      "level": 29,
      "build_time": 313920,
      "increased_power": 500,
      "requirements": [
        {
          "name": "Operations",
          "level": 29
        },
        {
          "name": "Dilithium Generator C",
          "level": 29
        }
      ],
      "build_costs": {
        "resources": [
          {
            "type": "tritanium",
            "value": 2665000
          },
          {
            "type": "parsteel",
            "value": 3624400
          }
        ],
        "materials": [],
        "others": []
      },
      "bonuses": {
        "bonus1": 0,
        "bonus2": 0,
        "bonus3": 165,
        "bonus4": 1475
      }
    },
    {
      "level": 30,
      "build_time": 339840,
      "increased_power": 400,
      "requirements": [
        {
          "name": "Operations",
          "level": 30
        },
        {
          "name": "Dilithium Generator C",
          "level": 30
        }
      ],
      "build_costs": {
        "resources": [
          {
            "type": "tritanium",
            "value": 3900000
          },
          {
            "type": "parsteel",
            "value": 5304000
          }
        ],
        "materials": [],
        "others": []
      },
      "bonuses": {
        "bonus1": 0,
        "bonus2": 0,
        "bonus3": 195,
        "bonus4": 1750
      }
    },
    {
      "level": 31,
      "build_time": 446400,
      "increased_power": 550,
      "requirements": [
        {
          "name": "Operations",
          "level": 31
        },
        {
          "name": "Dilithium Generator C",
          "level": 31
        }
      ],
      "build_costs": {
        "resources": [
          {
            "type": "tritanium",
            "value": 6165000
          },
          {
            "type": "parsteel",
            "value": 8384400
          }
        ],
        "materials": [],
        "others": []
      },
      "bonuses": {
        "bonus1": 0,
        "bonus2": 0,
        "bonus3": 205,
        "bonus4": 1850
      }
    },
    {
      "level": 32,
      "build_time": 436320,
      "increased_power": 500,
      "requirements": [
        {
          "name": "Operations",
          "level": 32
        },
        {
          "name": "Dilithium Generator C",
          "level": 32
        }
      ],
      "build_costs": {
        "resources": [
          {
            "type": "tritanium",
            "value": 8905000
          },
          {
            "type": "parsteel",
            "value": 12110800
          }
        ],
        "materials": [],
        "others": []
      },
      "bonuses": {
        "bonus1": 0,
        "bonus2": 0,
        "bonus3": 210,
        "bonus4": 2052
      }
    },
    {
      "level": 33,
      "build_time": 633600,
      "increased_power": 750,
      "requirements": [
        {
          "name": "Operations",
          "level": 33
        },
        {
          "name": "Dilithium Generator C",
          "level": 33
        }
      ],
      "build_costs": {
        "resources": [
          {
            "type": "tritanium",
            "value": 13775000
          },
          {
            "type": "parsteel",
            "value": 18734000
          }
        ],
        "materials": [],
        "others": []
      },
      "bonuses": {
        "bonus1": 0,
        "bonus2": 0,
        "bonus3": 215,
        "bonus4": 2233
      }
    },
    {
      "level": 34,
      "build_time": 839520,
      "increased_power": 500,
      "requirements": [
        {
          "name": "Operations",
          "level": 34
        },
        {
          "name": "Dilithium Generator C",
          "level": 34
        }
      ],
      "build_costs": {
        "resources": [
          {
            "type": "tritanium",
            "value": 21750000
          },
          {
            "type": "parsteel",
            "value": 29580000
          }
        ],
        "materials": [],
        "others": []
      },
      "bonuses": {
        "bonus1": 0,
        "bonus2": 0,
        "bonus3": 225,
        "bonus4": 2349
      }
    },
    {
      "level": 35,
      "build_time": 1107360,
      "increased_power": 750,
      "requirements": [
        {
          "name": "Operations",
          "level": 35
        },
        {
          "name": "Dilithium Generator C",
          "level": 35
        }
      ],
      "build_costs": {
        "resources": [
          {
            "type": "tritanium",
            "value": 33660000
          },
          {
            "type": "parsteel",
            "value": 45777600
          }
        ],
        "materials": [],
        "others": []
      },
      "bonuses": {
        "bonus1": 0,
        "bonus2": 0,
        "bonus3": 260,
        "bonus4": 2914
      }
    },
    {
      "level": 36,
      "build_time": 1414080,
      "increased_power": 750,
      "requirements": [
        {
          "name": "Operations",
          "level": 36
        },
        {
          "name": "Dilithium Generator C",
          "level": 36
        }
      ],
      "build_costs": {
        "resources": [
          {
            "type": "tritanium",
            "value": 47430000
          },
          {
            "type": "parsteel",
            "value": 64504800
          }
        ],
        "materials": [],
        "others": []
      },
      "bonuses": {
        "bonus1": 0,
        "bonus2": 0,
        "bonus3": 265,
        "bonus4": 3159
      }
    },
    {
      "level": 37,
      "build_time": 1461600,
      "increased_power": 750,
      "requirements": [
        {
          "name": "Operations",
          "level": 37
        },
        {
          "name": "Dilithium Generator C",
          "level": 37
        }
      ],
      "build_costs": {
        "resources": [
          {
            "type": "tritanium",
            "value": 72900000
          },
          {
            "type": "parsteel",
            "value": 99144000
          }
        ],
        "materials": [],
        "others": []
      },
      "bonuses": {
        "bonus1": 0,
        "bonus2": 0,
        "bonus3": 275,
        "bonus4": 3292
      }
    },
    {
      "level": 38,
      "build_time": 2370240,
      "increased_power": 1000,
      "requirements": [
        {
          "name": "Operations",
          "level": 38
        },
        {
          "name": "Dilithium Generator C",
          "level": 38
        }
      ],
      "build_costs": {
        "resources": [
          {
            "type": "tritanium",
            "value": 113400000
          },
          {
            "type": "parsteel",
            "value": 154224000
          }
        ],
        "materials": [],
        "others": []
      },
      "bonuses": {
        "bonus1": 0,
        "bonus2": 0,
        "bonus3": 280,
        "bonus4": 3586
      }
    },
    {
      "level": 39,
      "build_time": 3146400,
      "increased_power": 750,
      "requirements": [
        {
          "name": "Operations",
          "level": 39
        },
        {
          "name": "Dilithium Generator C",
          "level": 39
        }
      ],
      "build_costs": {
        "resources": [
          {
            "type": "tritanium",
            "value": 193500000
          },
          {
            "type": "parsteel",
            "value": 263160000
          }
        ],
        "materials": [],
        "others": []
      },
      "bonuses": {
        "bonus1": 0,
        "bonus2": 0,
        "bonus3": 290,
        "bonus4": 3978
      }
    },
    {
      "level": 40,
      "build_time": 5584320,
      "increased_power": 1000,
      "requirements": [
        {
          "name": "Operations",
          "level": 40
        },
        {
          "name": "Dilithium Generator C",
          "level": 40
        }
      ],
      "build_costs": {
        "resources": [
          {
            "type": "tritanium",
            "value": 301000000
          },
          {
            "type": "parsteel",
            "value": 1146208000
          }
        ],
        "materials": [],
        "others": []
      },
      "bonuses": {
        "bonus1": 0,
        "bonus2": 0,
        "bonus3": 365,
        "bonus4": 5011
      }
    },
    {
      "level": 41,
      "build_time": 5234400,
      "increased_power": 1000,
      "requirements": [
        {
          "name": "Operations",
          "level": 41
        },
        {
          "name": "Dilithium Generator C",
          "level": 41
        }
      ],
      "build_costs": {
        "resources": [
          {
            "type": "tritanium",
            "value": 430000000
          },
          {
            "type": "parsteel",
            "value": 1169600000
          }
        ],
        "materials": [],
        "others": []
      },
      "bonuses": {
        "bonus1": 0,
        "bonus2": 0,
        "bonus3": 370,
        "bonus4": 5486
      }
    },
    {
      "level": 42,
      "build_time": 8045280,
      "increased_power": 1000,
      "requirements": [
        {
          "name": "Operations",
          "level": 42
        },
        {
          "name": "Dilithium Generator C",
          "level": 42
        }
      ],
      "build_costs": {
        "resources": [
          {
            "type": "tritanium",
            "value": 640500000
          },
          {
            "type": "parsteel",
            "value": 1742160000
          }
        ],
        "materials": [],
        "others": []
      },
      "bonuses": {
        "bonus1": 0,
        "bonus2": 0,
        "bonus3": 380,
        "bonus4": 6199
      }
    },
    {
      "level": 43,
      "build_time": 10630080,
      "increased_power": 1250,
      "requirements": [
        {
          "name": "Operations",
          "level": 43
        },
        {
          "name": "Dilithium Generator C",
          "level": 43
        }
      ],
      "build_costs": {
        "resources": [
          {
            "type": "tritanium",
            "value": 915000000
          },
          {
            "type": "parsteel",
            "value": 2488800000
          }
        ],
        "materials": [],
        "others": []
      },
      "bonuses": {
        "bonus1": 0,
        "bonus2": 0,
        "bonus3": 390,
        "bonus4": 6335
      }
    },
    {
      "level": 44,
      "build_time": 13874400,
      "increased_power": 1250,
      "requirements": [
        {
          "name": "Operations",
          "level": 44
        },
        {
          "name": "Dilithium Generator C",
          "level": 44
        }
      ],
      "build_costs": {
        "resources": [
          {
            "type": "tritanium",
            "value": 1372500000
          },
          {
            "type": "parsteel",
            "value": 3733200000
          }
        ],
        "materials": [],
        "others": []
      },
      "bonuses": {
        "bonus1": 0,
        "bonus2": 0,
        "bonus3": 400,
        "bonus4": 7200
      }
    },
    {
      "level": 45,
      "build_time": 17912160,
      "increased_power": 1250,
      "requirements": [
        {
          "name": "Operations",
          "level": 45
        },
        {
          "name": "Dilithium Generator C",
          "level": 45
        }
      ],
      "build_costs": {
        "resources": [
          {
            "type": "tritanium",
            "value": 1950000000
          },
          {
            "type": "parsteel",
            "value": 5304000000
          }
        ],
        "materials": [],
        "others": []
      },
      "bonuses": {
        "bonus1": 0,
        "bonus2": 0,
        "bonus3": 465,
        "bonus4": 9394
      }
    },
    {
      "level": 46,
      "build_time": 22896000,
      "increased_power": 1250,
      "requirements": [
        {
          "name": "Operations",
          "level": 46
        },
        {
          "name": "Dilithium Generator C",
          "level": 46
        }
      ],
      "build_costs": {
        "resources": [
          {
            "type": "tritanium",
            "value": 2681250000
          },
          {
            "type": "parsteel",
            "value": 7293000000
          }
        ],
        "materials": [],
        "others": []
      },
      "bonuses": {
        "bonus1": 0,
        "bonus2": 0,
        "bonus3": 475,
        "bonus4": 9619
      }
    },
    {
      "level": 47,
      "build_time": 29004480,
      "increased_power": 1500,
      "requirements": [
        {
          "name": "Operations",
          "level": 47
        },
        {
          "name": "Dilithium Generator C",
          "level": 47
        }
      ],
      "build_costs": {
        "resources": [
          {
            "type": "tritanium",
            "value": 3900000000
          },
          {
            "type": "parsteel",
            "value": 10608000000
          }
        ],
        "materials": [],
        "others": []
      },
      "bonuses": {
        "bonus1": 0,
        "bonus2": 0,
        "bonus3": 485,
        "bonus4": 9844
      }
    },
    {
      "level": 48,
      "build_time": 36440640,
      "increased_power": 1500,
      "requirements": [
        {
          "name": "Operations",
          "level": 48
        },
        {
          "name": "Dilithium Generator C",
          "level": 48
        }
      ],
      "build_costs": {
        "resources": [
          {
            "type": "tritanium",
            "value": 6300000000
          },
          {
            "type": "parsteel",
            "value": 17136000000
          }
        ],
        "materials": [],
        "others": []
      },
      "bonuses": {
        "bonus1": 0,
        "bonus2": 0,
        "bonus3": 495,
        "bonus4": 10013
      }
    },
    {
      "level": 49,
      "build_time": 45434880,
      "increased_power": 1500,
      "requirements": [
        {
          "name": "Operations",
          "level": 49
        },
        {
          "name": "Dilithium Generator C",
          "level": 49
        }
      ],
      "build_costs": {
        "resources": [
          {
            "type": "tritanium",
            "value": 10500000000
          },
          {
            "type": "parsteel",
            "value": 28560000000
          }
        ],
        "materials": [],
        "others": []
      },
      "bonuses": {
        "bonus1": 0,
        "bonus2": 0,
        "bonus3": 510,
        "bonus4": 10350
      }
    },
    {
      "level": 50,
      "build_time": 56250720,
      "increased_power": 1500,
      "requirements": [
        {
          "name": "Operations",
          "level": 50
        },
        {
          "name": "Dilithium Generator C",
          "level": 50
        }
      ],
      "build_costs": {
        "resources": [
          {
            "type": "tritanium",
            "value": 18375000000
          },
          {
            "type": "parsteel",
            "value": 49980000000
          }
        ],
        "materials": [],
        "others": []
      },
      "bonuses": {
        "bonus1": 0,
        "bonus2": 0,
        "bonus3": 620,
        "bonus4": 12600
      }
    },
    {
      "level": 51,
      "build_time": 59626080,
      "increased_power": 2000,
      "requirements": [
        {
          "name": "Operations",
          "level": 51
        },
        {
          "name": "Dilithium Generator C",
          "level": 51
        }
      ],
      "build_costs": {
        "resources": [
          {
            "type": "tritanium",
            "value": 39000000000
          },
          {
            "type": "parsteel",
            "value": 249288000000
          }
        ],
        "materials": [],
        "others": []
      },
      "bonuses": {
        "bonus1": 0,
        "bonus2": 0,
        "bonus3": 635,
        "bonus4": 12891
      }
    },
    {
      "level": 52,
      "build_time": 63204480,
      "increased_power": 1500,
      "requirements": [
        {
          "name": "Operations",
          "level": 52
        },
        {
          "name": "Dilithium Generator C",
          "level": 52
        }
      ],
      "build_costs": {
        "resources": [
          {
            "type": "tritanium",
            "value": 66300000000
          },
          {
            "type": "parsteel",
            "value": 450840000000
          }
        ],
        "materials": [],
        "others": []
      },
      "bonuses": {
        "bonus1": 0,
        "bonus2": 0,
        "bonus3": 650,
        "bonus4": 13195
      }
    },
    {
      "level": 53,
      "build_time": 66996000,
      "increased_power": 2000,
      "requirements": [
        {
          "name": "Operations",
          "level": 53
        },
        {
          "name": "Dilithium Generator C",
          "level": 53
        }
      ],
      "build_costs": {
        "resources": [
          {
            "type": "tritanium",
            "value": 116000000000
          },
          {
            "type": "parsteel",
            "value": 757248000000
          }
        ],
        "materials": [],
        "others": []
      },
      "bonuses": {
        "bonus1": 0,
        "bonus2": 0,
        "bonus3": 655,
        "bonus4": 13297
      }
    },
    {
      "level": 54,
      "build_time": 71016480,
      "increased_power": 2000,
      "requirements": [
        {
          "name": "Operations",
          "level": 54
        },
        {
          "name": "Dilithium Generator C",
          "level": 54
        }
      ],
      "build_costs": {
        "resources": [
          {
            "type": "tritanium",
            "value": 174000000000
          },
          {
            "type": "parsteel",
            "value": 1135872000000
          }
        ],
        "materials": [],
        "others": []
      },
      "bonuses": {
        "bonus1": 0,
        "bonus2": 0,
        "bonus3": 670,
        "bonus4": 13601
      }
    },
    {
      "level": 55,
      "build_time": 75277440,
      "increased_power": 2000,
      "requirements": [
        {
          "name": "Operations",
          "level": 55
        },
        {
          "name": "Dilithium Generator C",
          "level": 55
        }
      ],
      "build_costs": {
        "resources": [
          {
            "type": "tritanium",
            "value": 273000000000
          },
          {
            "type": "parsteel",
            "value": 1930656000000
          }
        ],
        "materials": [],
        "others": []
      },
      "bonuses": {
        "bonus1": 0,
        "bonus2": 0,
        "bonus3": 800,
        "bonus4": 16240
      }
    },
    {
      "level": 56,
      "build_time": 79793280,
      "increased_power": 2000,
      "requirements": [
        {
          "name": "Operations",
          "level": 56
        },
        {
          "name": "Dilithium Generator C",
          "level": 56
        }
      ],
      "build_costs": {
        "resources": [
          {
            "type": "tritanium",
            "value": 429000000000
          },
          {
            "type": "parsteel",
            "value": 3033888000000
          }
        ],
        "materials": [],
        "others": []
      },
      "bonuses": {
        "bonus1": 0,
        "bonus2": 0,
        "bonus3": 815,
        "bonus4": 16545
      }
    },
    {
      "level": 57,
      "build_time": 84581280,
      "increased_power": 2000,
      "requirements": [
        {
          "name": "Operations",
          "level": 57
        },
        {
          "name": "Dilithium Generator C",
          "level": 57
        }
      ],
      "build_costs": {
        "resources": [
          {
            "type": "tritanium",
            "value": 671600000000
          },
          {
            "type": "parsteel",
            "value": 4749555200000
          }
        ],
        "materials": [],
        "others": []
      },
      "bonuses": {
        "bonus1": 0,
        "bonus2": 0,
        "bonus3": 830,
        "bonus4": 16849
      }
    },
    {
      "level": 58,
      "build_time": 89655840,
      "increased_power": 2500,
      "requirements": [
        {
          "name": "Operations",
          "level": 58
        },
        {
          "name": "Dilithium Generator C",
          "level": 58
        }
      ],
      "build_costs": {
        "resources": [
          {
            "type": "tritanium",
            "value": 1051200000000
          },
          {
            "type": "parsteel",
            "value": 6862233600000
          }
        ],
        "materials": [],
        "others": []
      },
      "bonuses": {
        "bonus1": 0,
        "bonus2": 0,
        "bonus3": 845,
        "bonus4": 17154
      }
    },
    {
      "level": 59,
      "build_time": 95035680,
      "increased_power": 2500,
      "requirements": [
        {
          "name": "Operations",
          "level": 59
        },
        {
          "name": "Dilithium Generator C",
          "level": 59
        }
      ],
      "build_costs": {
        "resources": [
          {
            "type": "tritanium",
            "value": 1576800000000
          },
          {
            "type": "parsteel",
            "value": 10293350400000
          }
        ],
        "materials": [],
        "others": []
      },
      "bonuses": {
        "bonus1": 0,
        "bonus2": 0,
        "bonus3": 865,
        "bonus4": 17560
      }
    },
    {
      "level": 60,
      "build_time": 100738080,
      "increased_power": 2500,
      "requirements": [
        {
          "name": "Operations",
          "level": 60
        },
        {
          "name": "Dilithium Generator C",
          "level": 60
        }
      ],
      "build_costs": {
        "resources": [
          {
            "type": "tritanium",
            "value": 2462500000000
          },
          {
            "type": "parsteel",
            "value": 16075200000000
          }
        ],
        "materials": [],
        "others": []
      },
      "bonuses": {
        "bonus1": 0,
        "bonus2": 0,
        "bonus3": 1000,
        "bonus4": 20300
      }
    },
    {
      "level": 61,
      "build_time": 102752640,
      "increased_power": 3000,
      "requirements": [
        {
          "name": "Operations",
          "level": 61
        },
        {
          "name": "Dilithium Generator C",
          "level": 61
        }
      ],
      "build_costs": {
        "resources": [
          {
            "type": "tritanium",
            "value": 2955000000000
          },
          {
            "type": "parsteel",
            "value": 19290240000000
          }
        ],
        "materials": [],
        "others": []
      },
      "bonuses": {
        "bonus1": 1,
        "bonus2": 25,
        "bonus3": 0,
        "bonus4": 0
      }
    },
    {
      "level": 62,
      "build_time": 2697120,
      "increased_power": 3000,
      "requirements": [
        {
          "name": "Operations",
          "level": 62
        },
        {
          "name": "Dilithium Generator C",
          "level": 62
        }
      ],
      "build_costs": {
        "resources": [
          {
            "type": "\u03c3-tritanium",
            "value": 130500
          },
          {
            "type": "\u03c3-parsteel",
            "value": 177480
          }
        ],
        "materials": [],
        "others": []
      },
      "bonuses": {
        "bonus1": 2,
        "bonus2": 45,
        "bonus3": 0,
        "bonus4": 0
      }
    },
    {
      "level": 63,
      "build_time": 3640320,
      "increased_power": 3500,
      "requirements": [
        {
          "name": "Operations",
          "level": 63
        },
        {
          "name": "Dilithium Generator C",
          "level": 63
        }
      ],
      "build_costs": {
        "resources": [
          {
            "type": "\u03c3-tritanium",
            "value": 274500
          },
          {
            "type": "\u03c3-parsteel",
            "value": 522648
          }
        ],
        "materials": [],
        "others": []
      },
      "bonuses": {
        "bonus1": 3,
        "bonus2": 60,
        "bonus3": 0,
        "bonus4": 0
      }
    },
    {
      "level": 64,
      "build_time": 4914720,
      "increased_power": 3500,
      "requirements": [
        {
          "name": "Operations",
          "level": 64
        },
        {
          "name": "Dilithium Generator C",
          "level": 64
        }
      ],
      "build_costs": {
        "resources": [
          {
            "type": "\u03c3-tritanium",
            "value": 619750
          },
          {
            "type": "\u03c3-parsteel",
            "value": 1222147
          }
        ],
        "materials": [],
        "others": []
      },
      "bonuses": {
        "bonus1": 4,
        "bonus2": 75,
        "bonus3": 0,
        "bonus4": 0
      }
    },
    {
      "level": 65,
      "build_time": 6635520,
      "increased_power": 4000,
      "requirements": [
        {
          "name": "Operations",
          "level": 65
        },
        {
          "name": "Dilithium Generator C",
          "level": 65
        }
      ],
      "build_costs": {
        "resources": [
          {
            "type": "\u03c3-tritanium",
            "value": 1179375
          },
          {
            "type": "\u03c3-parsteel",
            "value": 2405925
          }
        ],
        "materials": [],
        "others": []
      },
      "bonuses": {
        "bonus1": 5,
        "bonus2": 95,
        "bonus3": 0,
        "bonus4": 0
      }
    },
    {
      "level": 66,
      "build_time": 8958240,
      "increased_power": 4000,
      "requirements": [
        {
          "name": "Operations",
          "level": 66
        },
        {
          "name": "Dilithium Generator C",
          "level": 66
        }
      ],
      "build_costs": {
        "resources": [
          {
            "type": "\u03c3-tritanium",
            "value": 2007250
          },
          {
            "type": "\u03c3-parsteel",
            "value": 3002846
          }
        ],
        "materials": [],
        "others": []
      },
      "bonuses": {
        "bonus1": 6,
        "bonus2": 120,
        "bonus3": 0,
        "bonus4": 0
      }
    },
    {
      "level": 67,
      "build_time": 12093120,
      "increased_power": 4000,
      "requirements": [
        {
          "name": "Operations",
          "level": 67
        },
        {
          "name": "Dilithium Generator C",
          "level": 67
        }
      ],
      "build_costs": {
        "resources": [
          {
            "type": "\u03c3-tritanium",
            "value": 2897500
          },
          {
            "type": "\u03c3-parsteel",
            "value": 3940600
          }
        ],
        "materials": [],
        "others": []
      },
      "bonuses": {
        "bonus1": 7,
        "bonus2": 145,
        "bonus3": 0,
        "bonus4": 0
      }
    },
    {
      "level": 68,
      "build_time": 15721920,
      "increased_power": 4000,
      "requirements": [
        {
          "name": "Operations",
          "level": 68
        },
        {
          "name": "Dilithium Generator C",
          "level": 68
        }
      ],
      "build_costs": {
        "resources": [
          {
            "type": "\u03c3-tritanium",
            "value": 4037500
          },
          {
            "type": "\u03c3-parsteel",
            "value": 5491000
          }
        ],
        "materials": [],
        "others": []
      },
      "bonuses": {
        "bonus1": 9,
        "bonus2": 175,
        "bonus3": 0,
        "bonus4": 0
      }
    },
    {
      "level": 69,
      "build_time": 20437920,
      "increased_power": 4000,
      "requirements": [
        {
          "name": "Operations",
          "level": 69
        },
        {
          "name": "Dilithium Generator C",
          "level": 69
        }
      ],
      "build_costs": {
        "resources": [
          {
            "type": "\u03c3-tritanium",
            "value": 5652500
          },
          {
            "type": "\u03c3-parsteel",
            "value": 7687400
          }
        ],
        "materials": [],
        "others": []
      },
      "bonuses": {
        "bonus1": 11,
        "bonus2": 220,
        "bonus3": 0,
        "bonus4": 0
      }
    },
    {
      "level": 70,
      "build_time": 26569440,
      "increased_power": 5000,
      "requirements": [
        {
          "name": "Operations",
          "level": 70
        },
        {
          "name": "Dilithium Generator C",
          "level": 70
        }
      ],
      "build_costs": {
        "resources": [
          {
            "type": "\u03c3-tritanium",
            "value": 7932500
          },
          {
            "type": "\u03c3-parsteel",
            "value": 10788200
          }
        ],
        "materials": [],
        "others": []
      },
      "bonuses": {
        "bonus1": 14,
        "bonus2": 265,
        "bonus3": 0,
        "bonus4": 0
      }
    }
  ],
  "bonuses": {
    "bonus1": {
      "name": "\u03a3-Dilithium Production",
      "percentage": false
    },
    "bonus2": {
      "name": "\u03a3-Dilithium Storage",
      "percentage": false
    },
    "bonus3": {
      "name": "Dilithium Production",
      "percentage": false
    },
    "bonus4": {
      "name": "Dilithium Storage",
      "percentage": false
    }
  }
}
