{
  "building_name": "Tritanium Generator H",
  "description": "Produces Tritanium, an alloy many times harder than diamonds, used to construct mighty ships. Upgrading Tritanium Generators increases the amount that is produced, and unlocks the production of \u03a3-Tritanium at high levels.",
  "levels": [
    {
      "level": 1,
      "build_time": 30,
      "increased_power": 10,
      "requirements": [
        {
          "name": "Operations",
          "level": 50
        },
        {
          "name": "Tritanium Generator F",
          "level": 1
        }
      ],
      "build_costs": {
        "resources": [
          {
            "type": "parsteel",
            "value": 300
          }
        ],
        "materials": [],
        "others": []
      },
      "bonuses": {
        "bonus1": 0,
        "bonus2": 0,
        "bonus3": 15,
        "bonus4": 8
      }
    },
    {
      "level": 2,
      "build_time": 60,
      "increased_power": 10,
      "requirements": [
        {
          "name": "Operations",
          "level": 2
        },
        {
          "name": "Tritanium Generator F",
          "level": 2
        }
      ],
      "build_costs": {
        "resources": [
          {
            "type": "parsteel",
            "value": 400
          }
        ],
        "materials": [],
        "others": []
      },
      "bonuses": {
        "bonus1": 0,
        "bonus2": 0,
        "bonus3": 30,
        "bonus4": 30
      }
    },
    {
      "level": 3,
      "build_time": 120,
      "increased_power": 12,
      "requirements": [
        {
          "name": "Operations",
          "level": 3
        },
        {
          "name": "Tritanium Generator F",
          "level": 3
        }
      ],
      "build_costs": {
        "resources": [
          {
            "type": "parsteel",
            "value": 600
          }
        ],
        "materials": [],
        "others": []
      },
      "bonuses": {
        "bonus1": 0,
        "bonus2": 0,
        "bonus3": 45,
        "bonus4": 68
      }
    },
    {
      "level": 4,
      "build_time": 150,
      "increased_power": 13,
      "requirements": [
        {
          "name": "Operations",
          "level": 4
        },
        {
          "name": "Tritanium Generator F",
          "level": 4
        }
      ],
      "build_costs": {
        "resources": [
          {
            "type": "parsteel",
            "value": 1000
          }
        ],
        "materials": [],
        "others": []
      },
      "bonuses": {
        "bonus1": 0,
        "bonus2": 0,
        "bonus3": 60,
        "bonus4": 150
      }
    },
    {
      "level": 5,
      "build_time": 270,
      "increased_power": 15,
      "requirements": [
        {
          "name": "Operations",
          "level": 5
        },
        {
          "name": "Tritanium Generator F",
          "level": 5
        }
      ],
      "build_costs": {
        "resources": [
          {
            "type": "parsteel",
            "value": 1600
          }
        ],
        "materials": [],
        "others": []
      },
      "bonuses": {
        "bonus1": 0,
        "bonus2": 0,
        "bonus3": 75,
        "bonus4": 225
      }
    },
    {
      "level": 6,
      "build_time": 450,
      "increased_power": 20,
      "requirements": [
        {
          "name": "Operations",
          "level": 6
        },
        {
          "name": "Tritanium Generator F",
          "level": 6
        }
      ],
      "build_costs": {
        "resources": [
          {
            "type": "parsteel",
            "value": 2500
          }
        ],
        "materials": [],
        "others": []
      },
      "bonuses": {
        "bonus1": 0,
        "bonus2": 0,
        "bonus3": 91,
        "bonus4": 320
      }
    },
    {
      "level": 7,
      "build_time": 840,
      "increased_power": 20,
      "requirements": [
        {
          "name": "Operations",
          "level": 7
        },
        {
          "name": "Tritanium Generator F",
          "level": 7
        }
      ],
      "build_costs": {
        "resources": [
          {
            "type": "parsteel",
            "value": 3500
          }
        ],
        "materials": [],
        "others": []
      },
      "bonuses": {
        "bonus1": 0,
        "bonus2": 0,
        "bonus3": 105,
        "bonus4": 420
      }
    },
    {
      "level": 8,
      "build_time": 1200,
      "increased_power": 30,
      "requirements": [
        {
          "name": "Operations",
          "level": 8
        },
        {
          "name": "Tritanium Generator F",
          "level": 8
        }
      ],
      "build_costs": {
        "resources": [
          {
            "type": "parsteel",
            "value": 4250
          }
        ],
        "materials": [],
        "others": []
      },
      "bonuses": {
        "bonus1": 0,
        "bonus2": 0,
        "bonus3": 120,
        "bonus4": 600
      }
    },
    {
      "level": 9,
      "build_time": 1800,
      "increased_power": 40,
      "requirements": [
        {
          "name": "Operations",
          "level": 9
        },
        {
          "name": "Tritanium Generator F",
          "level": 9
        }
      ],
      "build_costs": {
        "resources": [
          {
            "type": "parsteel",
            "value": 5000
          }
        ],
        "materials": [],
        "others": []
      },
      "bonuses": {
        "bonus1": 0,
        "bonus2": 0,
        "bonus3": 135,
        "bonus4": 740
      }
    },
    {
      "level": 10,
      "build_time": 1920,
      "increased_power": 40,
      "requirements": [
        {
          "name": "Operations",
          "level": 10
        },
        {
          "name": "Tritanium Generator F",
          "level": 10
        }
      ],
      "build_costs": {
        "resources": [
          {
            "type": "parsteel",
            "value": 6000
          }
        ],
        "materials": [],
        "others": []
      },
      "bonuses": {
        "bonus1": 0,
        "bonus2": 0,
        "bonus3": 180,
        "bonus4": 1080
      }
    },
    {
      "level": 11,
      "build_time": 2040,
      "increased_power": 50,
      "requirements": [
        {
          "name": "Operations",
          "level": 11
        },
        {
          "name": "Tritanium Generator F",
          "level": 11
        }
      ],
      "build_costs": {
        "resources": [
          {
            "type": "parsteel",
            "value": 6800
          },
          {
            "type": "dilithium",
            "value": 8
          }
        ],
        "materials": [],
        "others": []
      },
      "bonuses": {
        "bonus1": 0,
        "bonus2": 0,
        "bonus3": 200,
        "bonus4": 1400
      }
    },
    {
      "level": 12,
      "build_time": 3720,
      "increased_power": 70,
      "requirements": [
        {
          "name": "Operations",
          "level": 12
        },
        {
          "name": "Tritanium Generator F",
          "level": 12
        }
      ],
      "build_costs": {
        "resources": [
          {
            "type": "parsteel",
            "value": 9350
          },
          {
            "type": "dilithium",
            "value": 22
          }
        ],
        "materials": [],
        "others": []
      },
      "bonuses": {
        "bonus1": 0,
        "bonus2": 0,
        "bonus3": 220,
        "bonus4": 1650
      }
    },
    {
      "level": 13,
      "build_time": 5400,
      "increased_power": 70,
      "requirements": [
        {
          "name": "Operations",
          "level": 13
        },
        {
          "name": "Tritanium Generator F",
          "level": 13
        }
      ],
      "build_costs": {
        "resources": [
          {
            "type": "parsteel",
            "value": 13600
          },
          {
            "type": "dilithium",
            "value": 48
          }
        ],
        "materials": [],
        "others": []
      },
      "bonuses": {
        "bonus1": 0,
        "bonus2": 0,
        "bonus3": 235,
        "bonus4": 2000
      }
    },
    {
      "level": 14,
      "build_time": 7800,
      "increased_power": 90,
      "requirements": [
        {
          "name": "Operations",
          "level": 14
        },
        {
          "name": "Tritanium Generator F",
          "level": 14
        }
      ],
      "build_costs": {
        "resources": [
          {
            "type": "parsteel",
            "value": 18700
          },
          {
            "type": "dilithium",
            "value": 88
          }
        ],
        "materials": [],
        "others": []
      },
      "bonuses": {
        "bonus1": 0,
        "bonus2": 0,
        "bonus3": 255,
        "bonus4": 2300
      }
    },
    {
      "level": 15,
      "build_time": 9900,
      "increased_power": 85,
      "requirements": [
        {
          "name": "Operations",
          "level": 15
        },
        {
          "name": "Tritanium Generator F",
          "level": 15
        }
      ],
      "build_costs": {
        "resources": [
          {
            "type": "parsteel",
            "value": 25500
          },
          {
            "type": "dilithium",
            "value": 150
          }
        ],
        "materials": [],
        "others": []
      },
      "bonuses": {
        "bonus1": 0,
        "bonus2": 0,
        "bonus3": 275,
        "bonus4": 2750
      }
    },
    {
      "level": 16,
      "build_time": 11700,
      "increased_power": 125,
      "requirements": [
        {
          "name": "Operations",
          "level": 16
        },
        {
          "name": "Tritanium Generator F",
          "level": 16
        }
      ],
      "build_costs": {
        "resources": [
          {
            "type": "parsteel",
            "value": 34000
          },
          {
            "type": "dilithium",
            "value": 200
          }
        ],
        "materials": [],
        "others": []
      },
      "bonuses": {
        "bonus1": 0,
        "bonus2": 0,
        "bonus3": 290,
        "bonus4": 3200
      }
    },
    {
      "level": 17,
      "build_time": 12600,
      "increased_power": 125,
      "requirements": [
        {
          "name": "Operations",
          "level": 17
        },
        {
          "name": "Tritanium Generator F",
          "level": 17
        }
      ],
      "build_costs": {
        "resources": [
          {
            "type": "parsteel",
            "value": 47600
          },
          {
            "type": "dilithium",
            "value": 280
          }
        ],
        "materials": [],
        "others": []
      },
      "bonuses": {
        "bonus1": 0,
        "bonus2": 0,
        "bonus3": 310,
        "bonus4": 3575
      }
    },
    {
      "level": 18,
      "build_time": 19200,
      "increased_power": 150,
      "requirements": [
        {
          "name": "Operations",
          "level": 18
        },
        {
          "name": "Tritanium Generator F",
          "level": 18
        }
      ],
      "build_costs": {
        "resources": [
          {
            "type": "parsteel",
            "value": 68000
          },
          {
            "type": "dilithium",
            "value": 400
          }
        ],
        "materials": [],
        "others": []
      },
      "bonuses": {
        "bonus1": 0,
        "bonus2": 0,
        "bonus3": 330,
        "bonus4": 4125
      }
    },
    {
      "level": 19,
      "build_time": 28080,
      "increased_power": 175,
      "requirements": [
        {
          "name": "Operations",
          "level": 19
        },
        {
          "name": "Tritanium Generator F",
          "level": 19
        }
      ],
      "build_costs": {
        "resources": [
          {
            "type": "parsteel",
            "value": 102000
          },
          {
            "type": "dilithium",
            "value": 600
          }
        ],
        "materials": [],
        "others": []
      },
      "bonuses": {
        "bonus1": 0,
        "bonus2": 0,
        "bonus3": 345,
        "bonus4": 4475
      }
    },
    {
      "level": 20,
      "build_time": 41760,
      "increased_power": 200,
      "requirements": [
        {
          "name": "Operations",
          "level": 20
        },
        {
          "name": "Tritanium Generator F",
          "level": 20
        }
      ],
      "build_costs": {
        "resources": [
          {
            "type": "parsteel",
            "value": 144500
          },
          {
            "type": "dilithium",
            "value": 850
          }
        ],
        "materials": [],
        "others": []
      },
      "bonuses": {
        "bonus1": 0,
        "bonus2": 0,
        "bonus3": 425,
        "bonus4": 6000
      }
    },
    {
      "level": 21,
      "build_time": 38160,
      "increased_power": 250,
      "requirements": [
        {
          "name": "Operations",
          "level": 21
        },
        {
          "name": "Tritanium Generator F",
          "level": 21
        }
      ],
      "build_costs": {
        "resources": [
          {
            "type": "parsteel",
            "value": 243270
          },
          {
            "type": "dilithium",
            "value": 1431
          }
        ],
        "materials": [],
        "others": []
      },
      "bonuses": {
        "bonus1": 0,
        "bonus2": 0,
        "bonus3": 450,
        "bonus4": 6300
      }
    },
    {
      "level": 22,
      "build_time": 59040,
      "increased_power": 200,
      "requirements": [
        {
          "name": "Operations",
          "level": 22
        },
        {
          "name": "Tritanium Generator F",
          "level": 22
        }
      ],
      "build_costs": {
        "resources": [
          {
            "type": "parsteel",
            "value": 378420
          },
          {
            "type": "dilithium",
            "value": 2226
          }
        ],
        "materials": [],
        "others": []
      },
      "bonuses": {
        "bonus1": 0,
        "bonus2": 0,
        "bonus3": 470,
        "bonus4": 6600
      }
    },
    {
      "level": 23,
      "build_time": 69840,
      "increased_power": 300,
      "requirements": [
        {
          "name": "Operations",
          "level": 23
        },
        {
          "name": "Tritanium Generator F",
          "level": 23
        }
      ],
      "build_costs": {
        "resources": [
          {
            "type": "parsteel",
            "value": 622710
          },
          {
            "type": "dilithium",
            "value": 3663
          }
        ],
        "materials": [],
        "others": []
      },
      "bonuses": {
        "bonus1": 0,
        "bonus2": 0,
        "bonus3": 490,
        "bonus4": 6900
      }
    },
    {
      "level": 24,
      "build_time": 85680,
      "increased_power": 200,
      "requirements": [
        {
          "name": "Operations",
          "level": 24
        },
        {
          "name": "Tritanium Generator F",
          "level": 24
        }
      ],
      "build_costs": {
        "resources": [
          {
            "type": "parsteel",
            "value": 981240
          },
          {
            "type": "dilithium",
            "value": 5772
          }
        ],
        "materials": [],
        "others": []
      },
      "bonuses": {
        "bonus1": 0,
        "bonus2": 0,
        "bonus3": 510,
        "bonus4": 7100
      }
    },
    {
      "level": 25,
      "build_time": 79200,
      "increased_power": 400,
      "requirements": [
        {
          "name": "Operations",
          "level": 25
        },
        {
          "name": "Tritanium Generator F",
          "level": 25
        }
      ],
      "build_costs": {
        "resources": [
          {
            "type": "parsteel",
            "value": 1591200
          },
          {
            "type": "dilithium",
            "value": 9360
          }
        ],
        "materials": [],
        "others": []
      },
      "bonuses": {
        "bonus1": 0,
        "bonus2": 0,
        "bonus3": 610,
        "bonus4": 8500
      }
    },
    {
      "level": 26,
      "build_time": 108000,
      "increased_power": 300,
      "requirements": [
        {
          "name": "Operations",
          "level": 26
        },
        {
          "name": "Tritanium Generator F",
          "level": 26
        }
      ],
      "build_costs": {
        "resources": [
          {
            "type": "parsteel",
            "value": 2486250
          },
          {
            "type": "dilithium",
            "value": 14625
          }
        ],
        "materials": [],
        "others": []
      },
      "bonuses": {
        "bonus1": 0,
        "bonus2": 0,
        "bonus3": 640,
        "bonus4": 9000
      }
    },
    {
      "level": 27,
      "build_time": 122400,
      "increased_power": 400,
      "requirements": [
        {
          "name": "Operations",
          "level": 27
        },
        {
          "name": "Tritanium Generator F",
          "level": 27
        }
      ],
      "build_costs": {
        "resources": [
          {
            "type": "parsteel",
            "value": 3794400
          },
          {
            "type": "dilithium",
            "value": 22320
          }
        ],
        "materials": [],
        "others": []
      },
      "bonuses": {
        "bonus1": 0,
        "bonus2": 0,
        "bonus3": 660,
        "bonus4": 9200
      }
    },
    {
      "level": 28,
      "build_time": 142560,
      "increased_power": 400,
      "requirements": [
        {
          "name": "Operations",
          "level": 28
        },
        {
          "name": "Tritanium Generator F",
          "level": 28
        }
      ],
      "build_costs": {
        "resources": [
          {
            "type": "parsteel",
            "value": 5691600
          },
          {
            "type": "dilithium",
            "value": 33480
          }
        ],
        "materials": [],
        "others": []
      },
      "bonuses": {
        "bonus1": 0,
        "bonus2": 0,
        "bonus3": 680,
        "bonus4": 9500
      }
    },
    {
      "level": 29,
      "build_time": 156960,
      "increased_power": 500,
      "requirements": [
        {
          "name": "Operations",
          "level": 29
        },
        {
          "name": "Tritanium Generator F",
          "level": 29
        }
      ],
      "build_costs": {
        "resources": [
          {
            "type": "parsteel",
            "value": 9061000
          },
          {
            "type": "dilithium",
            "value": 53300
          }
        ],
        "materials": [],
        "others": []
      },
      "bonuses": {
        "bonus1": 0,
        "bonus2": 0,
        "bonus3": 710,
        "bonus4": 9900
      }
    },
    {
      "level": 30,
      "build_time": 169920,
      "increased_power": 400,
      "requirements": [
        {
          "name": "Operations",
          "level": 30
        },
        {
          "name": "Tritanium Generator F",
          "level": 30
        }
      ],
      "build_costs": {
        "resources": [
          {
            "type": "parsteel",
            "value": 13260000
          },
          {
            "type": "dilithium",
            "value": 78000
          }
        ],
        "materials": [],
        "others": []
      },
      "bonuses": {
        "bonus1": 0,
        "bonus2": 0,
        "bonus3": 820,
        "bonus4": 11500
      }
    },
    {
      "level": 31,
      "build_time": 223200,
      "increased_power": 550,
      "requirements": [
        {
          "name": "Operations",
          "level": 31
        },
        {
          "name": "Tritanium Generator F",
          "level": 31
        }
      ],
      "build_costs": {
        "resources": [
          {
            "type": "parsteel",
            "value": 20961000
          },
          {
            "type": "dilithium",
            "value": 123300
          }
        ],
        "materials": [],
        "others": []
      },
      "bonuses": {
        "bonus1": 0,
        "bonus2": 0,
        "bonus3": 850,
        "bonus4": 11900
      }
    },
    {
      "level": 32,
      "build_time": 218880,
      "increased_power": 500,
      "requirements": [
        {
          "name": "Operations",
          "level": 32
        },
        {
          "name": "Tritanium Generator F",
          "level": 32
        }
      ],
      "build_costs": {
        "resources": [
          {
            "type": "parsteel",
            "value": 30277000
          },
          {
            "type": "dilithium",
            "value": 178100
          }
        ],
        "materials": [],
        "others": []
      },
      "bonuses": {
        "bonus1": 0,
        "bonus2": 0,
        "bonus3": 880,
        "bonus4": 13284
      }
    },
    {
      "level": 33,
      "build_time": 316800,
      "increased_power": 750,
      "requirements": [
        {
          "name": "Operations",
          "level": 33
        },
        {
          "name": "Tritanium Generator F",
          "level": 33
        }
      ],
      "build_costs": {
        "resources": [
          {
            "type": "parsteel",
            "value": 46835000
          },
          {
            "type": "dilithium",
            "value": 275500
          }
        ],
        "materials": [],
        "others": []
      },
      "bonuses": {
        "bonus1": 0,
        "bonus2": 0,
        "bonus3": 910,
        "bonus4": 14732
      }
    },
    {
      "level": 34,
      "build_time": 420480,
      "increased_power": 500,
      "requirements": [
        {
          "name": "Operations",
          "level": 34
        },
        {
          "name": "Tritanium Generator F",
          "level": 34
        }
      ],
      "build_costs": {
        "resources": [
          {
            "type": "parsteel",
            "value": 73950000
          },
          {
            "type": "dilithium",
            "value": 435000
          }
        ],
        "materials": [],
        "others": []
      },
      "bonuses": {
        "bonus1": 0,
        "bonus2": 0,
        "bonus3": 940,
        "bonus4": 15312
      }
    },
    {
      "level": 35,
      "build_time": 552960,
      "increased_power": 750,
      "requirements": [
        {
          "name": "Operations",
          "level": 35
        },
        {
          "name": "Tritanium Generator F",
          "level": 35
        }
      ],
      "build_costs": {
        "resources": [
          {
            "type": "parsteel",
            "value": 114444000
          },
          {
            "type": "dilithium",
            "value": 673200
          }
        ],
        "materials": [],
        "others": []
      },
      "bonuses": {
        "bonus1": 0,
        "bonus2": 0,
        "bonus3": 1070,
        "bonus4": 18600
      }
    },
    {
      "level": 36,
      "build_time": 707040,
      "increased_power": 750,
      "requirements": [
        {
          "name": "Operations",
          "level": 36
        },
        {
          "name": "Tritanium Generator F",
          "level": 36
        }
      ],
      "build_costs": {
        "resources": [
          {
            "type": "parsteel",
            "value": 161262000
          },
          {
            "type": "dilithium",
            "value": 948600
          }
        ],
        "materials": [],
        "others": []
      },
      "bonuses": {
        "bonus1": 0,
        "bonus2": 0,
        "bonus3": 1100,
        "bonus4": 20482
      }
    },
    {
      "level": 37,
      "build_time": 731520,
      "increased_power": 750,
      "requirements": [
        {
          "name": "Operations",
          "level": 37
        },
        {
          "name": "Tritanium Generator F",
          "level": 37
        }
      ],
      "build_costs": {
        "resources": [
          {
            "type": "parsteel",
            "value": 247860000
          },
          {
            "type": "dilithium",
            "value": 1458000
          }
        ],
        "materials": [],
        "others": []
      },
      "bonuses": {
        "bonus1": 0,
        "bonus2": 0,
        "bonus3": 1130,
        "bonus4": 21014
      }
    },
    {
      "level": 38,
      "build_time": 1185120,
      "increased_power": 1000,
      "requirements": [
        {
          "name": "Operations",
          "level": 38
        },
        {
          "name": "Tritanium Generator F",
          "level": 38
        }
      ],
      "build_costs": {
        "resources": [
          {
            "type": "parsteel",
            "value": 385560000
          },
          {
            "type": "dilithium",
            "value": 2268000
          }
        ],
        "materials": [],
        "others": []
      },
      "bonuses": {
        "bonus1": 0,
        "bonus2": 0,
        "bonus3": 1160,
        "bonus4": 23004
      }
    },
    {
      "level": 39,
      "build_time": 1573920,
      "increased_power": 750,
      "requirements": [
        {
          "name": "Operations",
          "level": 39
        },
        {
          "name": "Tritanium Generator F",
          "level": 39
        }
      ],
      "build_costs": {
        "resources": [
          {
            "type": "parsteel",
            "value": 657900000
          },
          {
            "type": "dilithium",
            "value": 3870000
          }
        ],
        "materials": [],
        "others": []
      },
      "bonuses": {
        "bonus1": 0,
        "bonus2": 0,
        "bonus3": 1190,
        "bonus4": 25551
      }
    },
    {
      "level": 40,
      "build_time": 2792160,
      "increased_power": 1000,
      "requirements": [
        {
          "name": "Operations",
          "level": 40
        },
        {
          "name": "Tritanium Generator F",
          "level": 40
        }
      ],
      "build_costs": {
        "resources": [
          {
            "type": "parsteel",
            "value": 2865520000
          },
          {
            "type": "dilithium",
            "value": 6020000
          }
        ],
        "materials": [],
        "others": []
      },
      "bonuses": {
        "bonus1": 0,
        "bonus2": 0,
        "bonus3": 1350,
        "bonus4": 28917
      }
    },
    {
      "level": 41,
      "build_time": 2616480,
      "increased_power": 1000,
      "requirements": [
        {
          "name": "Operations",
          "level": 41
        },
        {
          "name": "Tritanium Generator F",
          "level": 41
        }
      ],
      "build_costs": {
        "resources": [
          {
            "type": "parsteel",
            "value": 2924000000
          },
          {
            "type": "dilithium",
            "value": 8600000
          }
        ],
        "materials": [],
        "others": []
      },
      "bonuses": {
        "bonus1": 0,
        "bonus2": 0,
        "bonus3": 1380,
        "bonus4": 31845
      }
    },
    {
      "level": 42,
      "build_time": 4023360,
      "increased_power": 1000,
      "requirements": [
        {
          "name": "Operations",
          "level": 42
        },
        {
          "name": "Tritanium Generator F",
          "level": 42
        }
      ],
      "build_costs": {
        "resources": [
          {
            "type": "parsteel",
            "value": 4355400000
          },
          {
            "type": "dilithium",
            "value": 12810000
          }
        ],
        "materials": [],
        "others": []
      },
      "bonuses": {
        "bonus1": 0,
        "bonus2": 0,
        "bonus3": 1425,
        "bonus4": 36200
      }
    },
    {
      "level": 43,
      "build_time": 5315040,
      "increased_power": 1250,
      "requirements": [
        {
          "name": "Operations",
          "level": 43
        },
        {
          "name": "Tritanium Generator F",
          "level": 43
        }
      ],
      "build_costs": {
        "resources": [
          {
            "type": "parsteel",
            "value": 6222000000
          },
          {
            "type": "dilithium",
            "value": 18300000
          }
        ],
        "materials": [],
        "others": []
      },
      "bonuses": {
        "bonus1": 0,
        "bonus2": 0,
        "bonus3": 1450,
        "bonus4": 36653
      }
    },
    {
      "level": 44,
      "build_time": 6937920,
      "increased_power": 1250,
      "requirements": [
        {
          "name": "Operations",
          "level": 44
        },
        {
          "name": "Tritanium Generator F",
          "level": 44
        }
      ],
      "build_costs": {
        "resources": [
          {
            "type": "parsteel",
            "value": 9333000000
          },
          {
            "type": "dilithium",
            "value": 27450000
          }
        ],
        "materials": [],
        "others": []
      },
      "bonuses": {
        "bonus1": 0,
        "bonus2": 0,
        "bonus3": 1475,
        "bonus4": 41500
      }
    },
    {
      "level": 45,
      "build_time": 8955360,
      "increased_power": 1250,
      "requirements": [
        {
          "name": "Operations",
          "level": 45
        },
        {
          "name": "Tritanium Generator F",
          "level": 45
        }
      ],
      "build_costs": {
        "resources": [
          {
            "type": "parsteel",
            "value": 13260000000
          },
          {
            "type": "dilithium",
            "value": 39000000
          }
        ],
        "materials": [],
        "others": []
      },
      "bonuses": {
        "bonus1": 0,
        "bonus2": 0,
        "bonus3": 1725,
        "bonus4": 54563
      }
    },
    {
      "level": 46,
      "build_time": 11448000,
      "increased_power": 1250,
      "requirements": [
        {
          "name": "Operations",
          "level": 46
        },
        {
          "name": "Tritanium Generator F",
          "level": 46
        }
      ],
      "build_costs": {
        "resources": [
          {
            "type": "parsteel",
            "value": 18232500000
          },
          {
            "type": "dilithium",
            "value": 53625000
          }
        ],
        "materials": [],
        "others": []
      },
      "bonuses": {
        "bonus1": 0,
        "bonus2": 0,
        "bonus3": 1750,
        "bonus4": 55125
      }
    },
    {
      "level": 47,
      "build_time": 14502240,
      "increased_power": 1500,
      "requirements": [
        {
          "name": "Operations",
          "level": 47
        },
        {
          "name": "Tritanium Generator F",
          "level": 47
        }
      ],
      "build_costs": {
        "resources": [
          {
            "type": "parsteel",
            "value": 26520000000
          },
          {
            "type": "dilithium",
            "value": 78000000
          }
        ],
        "materials": [],
        "others": []
      },
      "bonuses": {
        "bonus1": 0,
        "bonus2": 0,
        "bonus3": 1800,
        "bonus4": 56813
      }
    },
    {
      "level": 48,
      "build_time": 18220320,
      "increased_power": 1500,
      "requirements": [
        {
          "name": "Operations",
          "level": 48
        },
        {
          "name": "Tritanium Generator F",
          "level": 48
        }
      ],
      "build_costs": {
        "resources": [
          {
            "type": "parsteel",
            "value": 42840000000
          },
          {
            "type": "dilithium",
            "value": 126000000
          }
        ],
        "materials": [],
        "others": []
      },
      "bonuses": {
        "bonus1": 0,
        "bonus2": 0,
        "bonus3": 1850,
        "bonus4": 58500
      }
    },
    {
      "level": 49,
      "build_time": 22717440,
      "increased_power": 1500,
      "requirements": [
        {
          "name": "Operations",
          "level": 49
        },
        {
          "name": "Tritanium Generator F",
          "level": 49
        }
      ],
      "build_costs": {
        "resources": [
          {
            "type": "parsteel",
            "value": 71400000000
          },
          {
            "type": "dilithium",
            "value": 210000000
          }
        ],
        "materials": [],
        "others": []
      },
      "bonuses": {
        "bonus1": 0,
        "bonus2": 0,
        "bonus3": 1875,
        "bonus4": 59063
      }
    },
    {
      "level": 50,
      "build_time": 28126080,
      "increased_power": 1500,
      "requirements": [
        {
          "name": "Operations",
          "level": 50
        },
        {
          "name": "Tritanium Generator F",
          "level": 50
        }
      ],
      "build_costs": {
        "resources": [
          {
            "type": "parsteel",
            "value": 124950000000
          },
          {
            "type": "dilithium",
            "value": 367500000
          }
        ],
        "materials": [],
        "others": []
      },
      "bonuses": {
        "bonus1": 0,
        "bonus2": 0,
        "bonus3": 2300,
        "bonus4": 72563
      }
    },
    {
      "level": 51,
      "build_time": 29813760,
      "increased_power": 2000,
      "requirements": [
        {
          "name": "Operations",
          "level": 51
        },
        {
          "name": "Tritanium Generator F",
          "level": 51
        }
      ],
      "build_costs": {
        "resources": [
          {
            "type": "parsteel",
            "value": 623220000000
          },
          {
            "type": "dilithium",
            "value": 780000000
          }
        ],
        "materials": [],
        "others": []
      },
      "bonuses": {
        "bonus1": 0,
        "bonus2": 0,
        "bonus3": 2350,
        "bonus4": 74250
      }
    },
    {
      "level": 52,
      "build_time": 31602240,
      "increased_power": 1500,
      "requirements": [
        {
          "name": "Operations",
          "level": 52
        },
        {
          "name": "Tritanium Generator F",
          "level": 52
        }
      ],
      "build_costs": {
        "resources": [
          {
            "type": "parsteel",
            "value": 1127100000000
          },
          {
            "type": "dilithium",
            "value": 1326000000
          }
        ],
        "materials": [],
        "others": []
      },
      "bonuses": {
        "bonus1": 0,
        "bonus2": 0,
        "bonus3": 2400,
        "bonus4": 75375
      }
    },
    {
      "level": 53,
      "build_time": 33498720,
      "increased_power": 2000,
      "requirements": [
        {
          "name": "Operations",
          "level": 53
        },
        {
          "name": "Tritanium Generator F",
          "level": 53
        }
      ],
      "build_costs": {
        "resources": [
          {
            "type": "parsteel",
            "value": 1893120000000
          },
          {
            "type": "dilithium",
            "value": 2320000000
          }
        ],
        "materials": [],
        "others": []
      },
      "bonuses": {
        "bonus1": 0,
        "bonus2": 0,
        "bonus3": 2425,
        "bonus4": 76500
      }
    },
    {
      "level": 54,
      "build_time": 35507520,
      "increased_power": 2000,
      "requirements": [
        {
          "name": "Operations",
          "level": 54
        },
        {
          "name": "Tritanium Generator F",
          "level": 54
        }
      ],
      "build_costs": {
        "resources": [
          {
            "type": "parsteel",
            "value": 2839680000000
          },
          {
            "type": "dilithium",
            "value": 3480000000
          }
        ],
        "materials": [],
        "others": []
      },
      "bonuses": {
        "bonus1": 0,
        "bonus2": 0,
        "bonus3": 2475,
        "bonus4": 78188
      }
    },
    {
      "level": 55,
      "build_time": 37638720,
      "increased_power": 2000,
      "requirements": [
        {
          "name": "Operations",
          "level": 55
        },
        {
          "name": "Tritanium Generator F",
          "level": 55
        }
      ],
      "build_costs": {
        "resources": [
          {
            "type": "parsteel",
            "value": 4826640000000
          },
          {
            "type": "dilithium",
            "value": 5460000000
          }
        ],
        "materials": [],
        "others": []
      },
      "bonuses": {
        "bonus1": 0,
        "bonus2": 0,
        "bonus3": 2950,
        "bonus4": 92813
      }
    },
    {
      "level": 56,
      "build_time": 39896640,
      "increased_power": 2000,
      "requirements": [
        {
          "name": "Operations",
          "level": 56
        },
        {
          "name": "Tritanium Generator F",
          "level": 56
        }
      ],
      "build_costs": {
        "resources": [
          {
            "type": "parsteel",
            "value": 7584720000000
          },
          {
            "type": "dilithium",
            "value": 8580000000
          }
        ],
        "materials": [],
        "others": []
      },
      "bonuses": {
        "bonus1": 0,
        "bonus2": 0,
        "bonus3": 3000,
        "bonus4": 94500
      }
    },
    {
      "level": 57,
      "build_time": 42289920,
      "increased_power": 2000,
      "requirements": [
        {
          "name": "Operations",
          "level": 57
        },
        {
          "name": "Tritanium Generator F",
          "level": 57
        }
      ],
      "build_costs": {
        "resources": [
          {
            "type": "parsteel",
            "value": 11873888000000
          },
          {
            "type": "dilithium",
            "value": 13432000000
          }
        ],
        "materials": [],
        "others": []
      },
      "bonuses": {
        "bonus1": 0,
        "bonus2": 0,
        "bonus3": 3050,
        "bonus4": 96188
      }
    },
    {
      "level": 58,
      "build_time": 44828640,
      "increased_power": 2500,
      "requirements": [
        {
          "name": "Operations",
          "level": 58
        },
        {
          "name": "Tritanium Generator F",
          "level": 58
        }
      ],
      "build_costs": {
        "resources": [
          {
            "type": "parsteel",
            "value": 17155584000000
          },
          {
            "type": "dilithium",
            "value": 21024000000
          }
        ],
        "materials": [],
        "others": []
      },
      "bonuses": {
        "bonus1": 0,
        "bonus2": 0,
        "bonus3": 3100,
        "bonus4": 97875
      }
    },
    {
      "level": 59,
      "build_time": 47517120,
      "increased_power": 2500,
      "requirements": [
        {
          "name": "Operations",
          "level": 59
        },
        {
          "name": "Tritanium Generator F",
          "level": 59
        }
      ],
      "build_costs": {
        "resources": [
          {
            "type": "parsteel",
            "value": 25733376000000
          },
          {
            "type": "dilithium",
            "value": 31536000000
          }
        ],
        "materials": [],
        "others": []
      },
      "bonuses": {
        "bonus1": 0,
        "bonus2": 0,
        "bonus3": 3175,
        "bonus4": 100125
      }
    },
    {
      "level": 60,
      "build_time": 50368320,
      "increased_power": 2500,
      "requirements": [
        {
          "name": "Operations",
          "level": 60
        },
        {
          "name": "Tritanium Generator F",
          "level": 60
        }
      ],
      "build_costs": {
        "resources": [
          {
            "type": "parsteel",
            "value": 40188000000000
          },
          {
            "type": "dilithium",
            "value": 49250000000
          }
        ],
        "materials": [],
        "others": []
      },
      "bonuses": {
        "bonus1": 0,
        "bonus2": 0,
        "bonus3": 3675,
        "bonus4": 115875
      }
    },
    {
      "level": 61,
      "build_time": 51376320,
      "increased_power": 3000,
      "requirements": [
        {
          "name": "Operations",
          "level": 61
        },
        {
          "name": "Tritanium Generator F",
          "level": 61
        }
      ],
      "build_costs": {
        "resources": [
          {
            "type": "parsteel",
            "value": 40188000000000
          },
          {
            "type": "dilithium",
            "value": 59100000000
          }
        ],
        "materials": [],
        "others": []
      },
      "bonuses": {
        "bonus1": 3,
        "bonus2": 90,
        "bonus3": 0,
        "bonus4": 0
      }
    },
    {
      "level": 62,
      "build_time": 1347840,
      "increased_power": 3000,
      "requirements": [
        {
          "name": "Operations",
          "level": 62
        },
        {
          "name": "Tritanium Generator F",
          "level": 62
        }
      ],
      "build_costs": {
        "resources": [
          {
            "type": "\u03c3-dilithium",
            "value": 2610
          },
          {
            "type": "\u03c3-parsteel",
            "value": 443700
          }
        ],
        "materials": [],
        "others": []
      },
      "bonuses": {
        "bonus1": 4,
        "bonus2": 110,
        "bonus3": 0,
        "bonus4": 0
      }
    },
    {
      "level": 63,
      "build_time": 1820160,
      "increased_power": 3500,
      "requirements": [
        {
          "name": "Operations",
          "level": 63
        },
        {
          "name": "Tritanium Generator F",
          "level": 63
        }
      ],
      "build_costs": {
        "resources": [
          {
            "type": "\u03c3-dilithium",
            "value": 5490
          },
          {
            "type": "\u03c3-parsteel",
            "value": 1306620
          }
        ],
        "materials": [],
        "others": []
      },
      "bonuses": {
        "bonus1": 5,
        "bonus2": 140,
        "bonus3": 0,
        "bonus4": 0
      }
    },
    {
      "level": 64,
      "build_time": 2458080,
      "increased_power": 3500,
      "requirements": [
        {
          "name": "Operations",
          "level": 64
        },
        {
          "name": "Tritanium Generator F",
          "level": 64
        }
      ],
      "build_costs": {
        "resources": [
          {
            "type": "\u03c3-dilithium",
            "value": 12395
          },
          {
            "type": "\u03c3-parsteel",
            "value": 3055368
          }
        ],
        "materials": [],
        "others": []
      },
      "bonuses": {
        "bonus1": 6,
        "bonus2": 175,
        "bonus3": 0,
        "bonus4": 0
      }
    },
    {
      "level": 65,
      "build_time": 3317760,
      "increased_power": 4000,
      "requirements": [
        {
          "name": "Operations",
          "level": 65
        },
        {
          "name": "Tritanium Generator F",
          "level": 65
        }
      ],
      "build_costs": {
        "resources": [
          {
            "type": "\u03c3-dilithium",
            "value": 23588
          },
          {
            "type": "\u03c3-parsteel",
            "value": 6014813
          }
        ],
        "materials": [],
        "others": []
      },
      "bonuses": {
        "bonus1": 8,
        "bonus2": 220,
        "bonus3": 0,
        "bonus4": 0
      }
    },
    {
      "level": 66,
      "build_time": 4478400,
      "increased_power": 4000,
      "requirements": [
        {
          "name": "Operations",
          "level": 66
        },
        {
          "name": "Tritanium Generator F",
          "level": 66
        }
      ],
      "build_costs": {
        "resources": [
          {
            "type": "\u03c3-dilithium",
            "value": 40145
          },
          {
            "type": "\u03c3-parsteel",
            "value": 7507115
          }
        ],
        "materials": [],
        "others": []
      },
      "bonuses": {
        "bonus1": 10,
        "bonus2": 275,
        "bonus3": 0,
        "bonus4": 0
      }
    },
    {
      "level": 67,
      "build_time": 6046560,
      "increased_power": 4000,
      "requirements": [
        {
          "name": "Operations",
          "level": 67
        },
        {
          "name": "Tritanium Generator F",
          "level": 67
        }
      ],
      "build_costs": {
        "resources": [
          {
            "type": "\u03c3-dilithium",
            "value": 57950
          },
          {
            "type": "\u03c3-parsteel",
            "value": 9851500
          }
        ],
        "materials": [],
        "others": []
      },
      "bonuses": {
        "bonus1": 13,
        "bonus2": 345,
        "bonus3": 0,
        "bonus4": 0
      }
    },
    {
      "level": 68,
      "build_time": 7860960,
      "increased_power": 4000,
      "requirements": [
        {
          "name": "Operations",
          "level": 68
        },
        {
          "name": "Tritanium Generator F",
          "level": 68
        }
      ],
      "build_costs": {
        "resources": [
          {
            "type": "\u03c3-dilithium",
            "value": 80750
          },
          {
            "type": "\u03c3-parsteel",
            "value": 13727500
          }
        ],
        "materials": [],
        "others": []
      },
      "bonuses": {
        "bonus1": 16,
        "bonus2": 430,
        "bonus3": 0,
        "bonus4": 0
      }
    },
    {
      "level": 69,
      "build_time": 10219680,
      "increased_power": 4000,
      "requirements": [
        {
          "name": "Operations",
          "level": 69
        },
        {
          "name": "Tritanium Generator F",
          "level": 69
        }
      ],
      "build_costs": {
        "resources": [
          {
            "type": "\u03c3-dilithium",
            "value": 113050
          },
          {
            "type": "\u03c3-parsteel",
            "value": 19218500
          }
        ],
        "materials": [],
        "others": []
      },
      "bonuses": {
        "bonus1": 20,
        "bonus2": 540,
        "bonus3": 0,
        "bonus4": 0
      }
    },
    {
      "level": 70,
      "build_time": 13285440,
      "increased_power": 5000,
      "requirements": [
        {
          "name": "Operations",
          "level": 70
        },
        {
          "name": "Tritanium Generator F",
          "level": 70
        }
      ],
      "build_costs": {
        "resources": [
          {
            "type": "\u03c3-dilithium",
            "value": 158650
          },
          {
            "type": "\u03c3-parsteel",
            "value": 26970500
          }
        ],
        "materials": [],
        "others": []
      },
      "bonuses": {
        "bonus1": 25,
        "bonus2": 675,
        "bonus3": 0,
        "bonus4": 0
      }
    }
  ],
  "bonuses": {
    "bonus1": {
      "name": "\u03a3-Tritanium Production",
      "percentage": false
    },
    "bonus2": {
      "name": "\u03a3-Tritanium Storage",
      "percentage": false
    },
    "bonus3": {
      "name": "Tritanium Production",
      "percentage": false
    },
    "bonus4": {
      "name": "Tritanium Storage",
      "percentage": false
    }
  }
}
