{
  "hostile_name": "Imperial Starfleet Warship",
  "description": "",
  "group": "mirror universe",
  "level": 42,
  "rarity": "common",
  "head_stats": {
    "attack": 7786154,
    "defense": 1237445,
    "health": 116484180
  },
  "systems": [],
  "ship_class": "battleship",
  "stats": {
    "attack": {
      "accuracy": 959151,
      "armor_pierce": 959151,
      "crit_chance": 0.1,
      "crit_damage": 1.5,
      "damage_per_round": 3573268,
      "shield_pierce": 188141
    },
    "defense": {
      "armor": 136599,
      "dodge": 60210,
      "shield_deflect": 50680
    },
    "health": {
      "hull_health": 139781017,
      "shield_health": 93187344
    }
  },
  "weapons": [
    {
      "firing_pattern": [
        2,
        2,
        2,
        2,
        2,
        2,
        2,
        2,
        2,
        2,
        2,
        2,
        2,
        2,
        2
      ],
      "quantity": 1,
      "weapon_stats": {
        "accuracy": 959151,
        "armor_pierce": 959151,
        "crit_chance": 0.1,
        "crit_damage": 1.5,
        "damage_per_round": 1786634,
        "max_damage": 809164,
        "min_damage": 744431,
        "shield_pierce": 188141
      },
      "weapon_type": "energy"
    },
    {
      "firing_pattern": [
        3,
        3,
        3,
        3,
        3,
        3,
        3,
        3,
        3,
        3,
        3,
        3,
        3,
        3,
        3
      ],
      "quantity": 1,
      "weapon_stats": {
        "accuracy": 959151,
        "armor_pierce": 959151,
        "crit_chance": 0.1,
        "crit_damage": 1.5,
        "damage_per_round": 1071980,
        "max_damage": 323666,
        "min_damage": 297772,
        "shield_pierce": 188141
      },
      "weapon_type": "energy"
    },
    {
      "firing_pattern": [
        2,
        2,
        2,
        2,
        2,
        2,
        2,
        2,
        2,
        2,
        2,
        2,
        2,
        2,
        2
      ],
      "quantity": 1,
      "weapon_stats": {
        "accuracy": 959151,
        "armor_pierce": 959151,
        "crit_chance": 0.1,
        "crit_damage": 1.5,
        "damage_per_round": 357326,
        "max_damage": 161833,
        "min_damage": 148886,
        "shield_pierce": 188141
      },
      "weapon_type": "energy"
    },
    {
      "firing_pattern": [
        2,
        2,
        2,
        2,
        2,
        2,
        2,
        2,
        2,
        2,
        2,
        2,
        2,
        2,
        2
      ],
      "quantity": 1,
      "weapon_stats": {
        "accuracy": 959151,
        "armor_pierce": 959151,
        "crit_chance": 0.1,
        "crit_damage": 1.5,
        "damage_per_round": 357326,
        "max_damage": 161833,
        "min_damage": 148886,
        "shield_pierce": 188141
      },
      "weapon_type": "kinetic"
    }
  ],
  "rewards": [],
  "utility": [
    {
      "impulse_speed": 65
    }
  ]
}
