{
  "hostile_name": "Xindi-Aquatic Enhanced Cruiser",
  "description": "",
  "group": "xindi-aquatic",
  "level": 57,
  "rarity": "common",
  "head_stats": {
    "attack": 322199357116,
    "defense": 24297390,
    "health": 4889240626756
  },
  "systems": [
    {
      "$ref": "systems/meedra_57"
    }
  ],
  "ship_class": "battleship",
  "stats": {
    "attack": {
      "accuracy": 1874774,
      "armor_pierce": 1874774,
      "crit_chance": 0.22,
      "crit_damage": 2.5,
      "damage_per_round": 322178088667,
      "shield_pierce": 3339935
    },
    "defense": {
      "armor": 4453236,
      "dodge": 203121,
      "shield_deflect": 203121
    },
    "health": {
      "hull_health": 5867088752107,
      "shield_health": 3911392501405
    }
  },
  "weapons": [
    {
      "firing_pattern": [
        10,
        10,
        10,
        10,
        10,
        10,
        10,
        10,
        10,
        10,
        10,
        10,
        10,
        10,
        10
      ],
      "quantity": 2,
      "weapon_stats": {
        "accuracy": 1874774,
        "armor_pierce": 1874774,
        "crit_chance": 0.01,
        "crit_damage": 1.5,
        "damage_per_round": 53479289,
        "max_damage": 5488433,
        "min_damage": 5049358,
        "shield_pierce": 3339935
      },
      "weapon_type": "kinetic"
    },
    {
      "firing_pattern": [
        10,
        10,
        10,
        10,
        10,
        10,
        10,
        10,
        10,
        10,
        10,
        10,
        10,
        10,
        10
      ],
      "quantity": 1,
      "weapon_stats": {
        "accuracy": 1874774,
        "armor_pierce": 1874774,
        "crit_chance": 0.1,
        "crit_damage": 1.5,
        "damage_per_round": 51936254,
        "max_damage": 4704371,
        "min_damage": 4328021,
        "shield_pierce": 3339935
      },
      "weapon_type": "kinetic"
    },
    {
      "firing_pattern": [
        10,
        0,
        0,
        0,
        0,
        0,
        0,
        0,
        0,
        0,
        0,
        0,
        0,
        0,
        0
      ],
      "quantity": 1,
      "weapon_stats": {
        "accuracy": 1874774,
        "armor_pierce": 1874774,
        "crit_chance": 1,
        "crit_damage": 7.5,
        "damage_per_round": 1919383470,
        "max_damage": 23521856,
        "min_damage": 21640108,
        "shield_pierce": 3339935
      },
      "weapon_type": "kinetic"
    },
    {
      "firing_pattern": [
        10,
        10,
        10,
        10,
        10,
        10,
        10,
        10,
        10,
        10,
        10,
        10,
        10,
        10,
        10
      ],
      "quantity": 1,
      "weapon_stats": {
        "accuracy": 1874774,
        "armor_pierce": 1874774,
        "crit_chance": 0.1,
        "crit_damage": 1.5,
        "damage_per_round": 115000000000,
        "max_damage": 10000000000,
        "min_damage": 10000000000,
        "shield_pierce": 3339935
      },
      "weapon_type": "energy"
    },
    {
      "firing_pattern": [
        9,
        9,
        9,
        9,
        9,
        9,
        9,
        9,
        9,
        9,
        9,
        9,
        9,
        9,
        9
      ],
      "quantity": 1,
      "weapon_stats": {
        "accuracy": 1874774,
        "armor_pierce": 1874774,
        "crit_chance": 0.1,
        "crit_damage": 1.5,
        "damage_per_round": 207000000000,
        "max_damage": 20000000000,
        "min_damage": 20000000000,
        "shield_pierce": 3339935
      },
      "weapon_type": "kinetic"
    }
  ],
  "rewards": [
    {
      "type": "tech module",
      "max_value": 1009390,
      "min_value": 1009390,
      "value": 1009390
    },
    {
      "type": "xindi scraps",
      "max_value": 6388,
      "min_value": 6388,
      "value": 6388
    }
  ],
  "utility": [
    {
      "impulse_speed": 25
    }
  ]
}
